{"publisher": "Alpha books", "isbn": "8936066700702", "description": "  Ch\u00e2n dung nh\u1eefng nh\u00e0 s\u00e1ng l\u1eadp t\u1eadp \u0111o\u00e0n Matsushita, Honda v\u00e0 Kyocera C\u00e2u chuy\u1ec7n v\u1ec1 ba v\u1ecb doanh nh\u00e2n huy\u1ec1n tho\u1ea1i c\u1ee7a n\u01b0\u1edbc Nh\u1eadt. Matsushita Konosuke, Honda Soichiro v\u00e0 Inamori Kazuo l\u00e0 nh\u1eefng con ng\u01b0\u1eddi c\u00f3 xu\u1ea5t th\u00e2n b\u00ecnh th\u01b0\u1eddng, n\u1ebfu kh\u00f4ng mu\u1ed1n l\u00e0 ngh\u00e8o kh\u00f3 trong x\u00e3 h\u1ed9i Nh\u1eadt B\u1ea3n. Matsushita l\u00e0 con nh\u00e0 n\u00f4ng d\u00e2n, Honda c\u00f3 cha l\u00e0 th\u1ee3 r\u00e8n, c\u00f2n Inamori l\u00e0 con th\u1ee3 in. Nh\u01b0ng h\u1ecd \u0111\u00e3 kh\u00f4ng ng\u1eebng th\u00e1ch th\u1ee9c nh\u1eefng gi\u1edbi h\u1ea1n, v\u01b0\u1ee3t qua m\u1ecdi tr\u1edf ng\u1ea1i \u0111\u1ec3 x\u00e2y d\u1ef1ng n\u00ean nh\u1eefng c\u00f4ng ty th\u00e0nh c\u00f4ng nh\u1ea5t trong t\u1ea1i Nh\u1eadt B\u1ea3n, \u0111\u00f3 l\u00e0 T\u1eadp \u0111o\u00e0n Matsushita, T\u1eadp \u0111o\u00e0n Honda v\u00e0 T\u1eadp \u0111o\u00e0n Kyocera. B\u00e0i h\u1ecdc m\u00e0 ng\u01b0\u1eddi ta c\u00f3 th\u1ec3 r\u00fat ra t\u1eeb ba v\u1ecb doanh nh\u00e2n huy\u1ec1n tho\u1ea1i c\u1ee7a n\u01b0\u1edbc Nh\u1eadt l\u00e0 g\u00ec? \u0110\u00f3 l\u00e0 xu\u1ea5t th\u00e2n ch\u1ec9 l\u00e0 \u0111i\u1ec1u ki\u1ec7n, kh\u00f4ng ph\u1ea3i c\u01a1 h\u1ed9i. Ng\u01b0\u1eddi c\u00f3 xu\u1ea5t th\u00e2n cao qu\u00fd, gi\u00e0u sang ch\u01b0a ch\u1eafc c\u00f3 th\u1ec3 l\u00e0m n\u00ean s\u1ef1 nghi\u1ec7p l\u1edbn. Ng\u01b0\u1ee3c l\u1ea1i, n\u1ebfu c\u00f3 l\u00f2ng quy\u1ebft t\u00e2m, kh\u00e1t khao h\u1ecdc h\u1ecfi v\u00e0 m\u1ed9t tr\u00e1i tim r\u1ed9ng m\u1edf, th\u00ec ch\u00fang ta ho\u00e0n to\u00e0n c\u00f3 th\u1ec3 l\u00e0m ch\u1ee7 t\u01b0\u01a1ng lai c\u1ee7a m\u00ecnh v\u00e0 tr\u1edf n\u00ean v\u0129 \u0111\u1ea1i. S\u1ebd th\u1ebf n\u00e0o n\u1ebfu Matsushita Konosuke ch\u1ecbu an ph\u1eadn l\u00e0m nh\u00e2n vi\u00ean cho m\u1ed9t c\u1eeda h\u00e0ng xe \u0111\u1ea1p t\u1ea1i Osaka? Ng\u00e0nh c\u00f4ng nghi\u1ec7p xe m\u00e1y v\u00e0 xe h\u01a1i Nh\u1eadt s\u1ebd ra sao n\u1ebfu Honda Soichiro ch\u1ec9 m\u00e3i \u1edf l\u1ea1i qu\u00ea nh\u00e0 t\u1ea1i Shizuoka? V\u00e0 n\u1ebfu Inamori Kazuo c\u1ee9 m\u00e3i t\u1ef1 ti v\u00ec m\u00ecnh ch\u1ec9 l\u00e0 m\u1ed9t c\u1eadu h\u1ecdc tr\u00f2 tr\u01b0\u1eddng t\u1ec9nh, th\u00ec li\u1ec7u c\u00f3 m\u1ed9t T\u1eadp \u0111o\u00e0n Kyocera l\u1eebng l\u1eaby nh\u01b0 ng\u00e0y nay? V\u1edbi l\u1ed1i k\u1ec3 chuy\u1ec7n h\u1ea5p d\u1eabn v\u00e0 lu\u00f4n \u0111\u01b0a ra nh\u1eefng b\u00e0i h\u1ecdc \u0111\u00fac k\u1ebft sau m\u1ed7i ch\u01b0\u01a1ng, cu\u1ed1n s\u00e1ch B\u1ed9 ba xu\u1ea5t ch\u00fang Nh\u1eadt B\u1ea3n s\u1ebd gi\u00fap b\u1ea1n \u0111\u1ecdc nh\u00ecn l\u1ea1i h\u00e0nh tr\u00ecnh cu\u1ed9c \u0111\u1eddi c\u1ee7a nh\u1eefng b\u1eadc doanh nh\u00e2n \u0111\u01b0\u1ee3c c\u1ea3 th\u1ebf gi\u1edbi tr\u1ecdng v\u1ecdng \u2013 Matsushita Konosuke, Honda Soichiro v\u00e0 Inamori Kazuo. B\u1ea1n s\u1ebd h\u1ecdc th\u00eam \u0111\u01b0\u1ee3c nhi\u1ec1u b\u00e0i h\u1ecdc v\u1ec1 tinh th\u1ea7n v\u00e0 tri\u1ebft l\u00fd kinh doanh c\u1ee7a ng\u01b0\u1eddi Nh\u1eadt t\u1eeb cu\u1ed9c \u0111\u1eddi v\u00e0 th\u00e0nh t\u1ef1u c\u1ee7a ba v\u1ecb doanh nh\u00e2n n\u00e0y.", "img": "https://www.vinabook.com/images/thumbnails/product/240x/220928_p69661m003.jpg", "author": "Jung Hyuk June", "class": "kinhte", "name": "B\u1ed9 Ba Xu\u1ea5t Ch\u00fang - Nh\u1eadt B\u1ea3n"}