{"publisher": "Minh Long", "isbn": "8936067598766", "description": "  \u201cH\u00e3y t\u1ef1 t\u1ea1o \u0111i\u1ec1u ki\u1ec7n thu\u1eadn l\u1ee3i cho m\u00ecnh, \u0111\u1eebng ph\u00f3 m\u1eb7c s\u1ef1 nghi\u1ec7p c\u1ee7a b\u1ea1n cho may r\u1ee7i\u201d, \u0111\u00f3 l\u00e0 nh\u1eefng c\u00e2u t\u1eeb m\u00e0 Kenneth \u0111\u00e3 vi\u1ebft trong m\u1ed9t cu\u1ed1n s\u00e1ch s\u00e2u s\u1eafc v\u00e0 thi\u1ebft th\u1ef1c m\u1ed9t c\u00e1ch tuy\u1ec7t v\u1eddi. Khi n\u00f3i \u0111\u1ebfn s\u1ef1 nghi\u1ec7p, th\u1ef1c t\u1ebf l\u00e0 nhi\u1ec1u ng\u01b0\u1eddi trong s\u1ed1 ch\u00fang ta tin v\u00e0o may r\u1ee7i nhi\u1ec1u h\u01a1n m\u1ee9c c\u1ea7n thi\u1ebft. N\u00f3 gi\u1ed1ng nh\u01b0 vi\u1ec7c ch\u00fang ta b\u01b0\u1edbc xu\u1ed1ng m\u1ed9t con thuy\u1ec1n \u0111\u1ec3 b\u1eaft \u0111\u1ea7u h\u00e0nh tr\u00ecnh s\u1ef1 nghi\u1ec7p r\u1ed3i \u0111\u1ec3 con thuy\u1ec1n \u0111\u00f3 tr\u00f4i n\u1ed5i m\u1ed9t c\u00e1ch v\u00f4 \u0111\u1ecbnh. Ch\u00fang ta xu\u00f4i theo d\u00f2ng v\u00e0 c\u00f3 th\u1ec3 s\u1ebd d\u1eebng ch\u00e2n \u1edf n\u01a1i n\u00e0o \u0111\u00f3 khi\u1ebfn b\u1ea3n th\u00e2n h\u00e0i l\u00f2ng v\u00e0 th\u1ecfa m\u00e3n, th\u1eadm ch\u00ed h\u01b0ng ph\u1ea5n. Nh\u01b0ng trong nhi\u1ec1u tr\u01b0\u1eddng h\u1ee3p, \u0111i\u1ec1u \u0111\u00f3 kh\u00f4ng x\u1ea3y ra. \u0110\u01b0\u1ee3c vi\u1ebft n\u00ean t\u1eeb ch\u00ednh tr\u1ea3i nghi\u1ec7m c\u1ee7a Kenneth qua v\u00f4 s\u1ed1 cu\u1ed9c h\u1ed9i th\u1ea3o, bu\u1ed5i ph\u1ecfng v\u1ea5n v\u00e0 n\u00f3i chuy\u1ec7n m\u00e0 anh \u0111\u00e3 ti\u1ebfn h\u00e0nh, cu\u1ed1n s\u00e1ch n\u00e0y d\u1ea1y ch\u00fang ta c\u00e1ch \u201cch\u00e8o thuy\u1ec1n\u201d, hay n\u00f3i c\u00e1ch kh\u00e1c l\u00e0 c\u00e1ch \u0111\u1ec3 ch\u00fang ta ki\u1ec3m so\u00e1t h\u00e0nh tr\u00ecnh s\u1ef1 nghi\u1ec7p c\u1ee7a m\u00ecnh. \u0110\u00e2y l\u00e0 m\u1ed9t nhi\u1ec7m v\u1ee5 kh\u00f4ng d\u1ec5 d\u00e0ng: c\u00f3 qu\u00e1 nhi\u1ec1u r\u1ee7i ro, nh\u1eefng b\u1ea5t \u1ed5n, nh\u1eefng ng\u00e3 r\u1ebd sai l\u1ea7m, nh\u1eefng c\u1ea1m b\u1eaby v\u00e0 c\u00e1m d\u1ed7 d\u1ecdc theo \u0111\u01b0\u1eddng \u0111i. M\u1ed9t trong nh\u1eefng c\u00e2u h\u1ecfi c\u01a1 b\u1ea3n nh\u1ea5t m\u00e0 ta ph\u1ea3i \u0111\u1ed1i m\u1eb7t l\u00e0 ta \u0111ang t\u00ecm ki\u1ebfm \u0111\u00edch \u0111\u1ebfn n\u00e0o. Tr\u00ean th\u1ef1c t\u1ebf, \u00fd t\u01b0\u1edfng c\u1ee7a ch\u00fang ta v\u1ec1 \u0111i\u1ec1u \u0111\u00f3 th\u01b0\u1eddng thay \u0111\u1ed5i theo th\u1eddi gian v\u00e0 kinh nghi\u1ec7m s\u1ed1ng. L\u00ed t\u01b0\u1edfng nh\u1ea5t, m\u1ee5c ti\u00eau c\u1ee7a ch\u00fang ta n\u00ean l\u00e0 t\u00ecm ki\u1ebfm m\u1ed9t khuynh h\u01b0\u1edbng, m\u1ed9t \u0111i\u1ec1u g\u00ec \u0111\u00f3 ta \u0111am m\u00ea. T\u1ea5t nhi\u00ean, ch\u00fang ta v\u1eabn c\u1ea7n th\u1eddi gian \u0111\u1ec3 t\u00ecm ra n\u00f3. Nh\u01b0ng kh\u00f4ng sao c\u1ea3, nh\u01b0 Kenneth n\u00f3i, ch\u00fang ta kh\u00f4ng c\u1ea7n ph\u1ea3i cu\u1ed1ng cu\u1ed3ng lo s\u1ee3 d\u00f9 cho kh\u00f4ng bi\u1ebft m\u00ecnh \u0111am m\u00ea \u0111i\u1ec1u g\u00ec. C\u00e2u tr\u1ea3 l\u1eddi \u1edf ngay trong ch\u00ednh ch\u00fang ta. T\u1ea5t c\u1ea3 nh\u1eefng g\u00ec ch\u00fang ta c\u1ea7n l\u00e0m l\u00e0 t\u1ef1 h\u1ecfi b\u1ea3n th\u00e2n nh\u1eefng c\u00e2u h\u1ecfi ph\u00f9 h\u1ee3p v\u00e0 tr\u1ea3 l\u1eddi ch\u00fang m\u1ed9t c\u00e1ch th\u00e0nh th\u1ef1c. Ch\u00fang l\u00e0 nh\u1eefng c\u00e2u h\u1ecfi v\u1ec1 kh\u1ea3 n\u0103ng, th\u00e0nh t\u00edch, m\u01a1 \u01b0\u1edbc v\u00e0 c\u01a1 h\u1ed9i c\u1ee7a ch\u00fang ta. V\u00e0 ch\u00fang c\u00f2n l\u00e0 v\u1ec1 nh\u1eefng \u01b0u ti\u00ean c\u00e1 nh\u00e2n: s\u1ef1 nghi\u1ec7p c\u1ee7a ch\u00fang ta tuy quan tr\u1ecdng nh\u01b0ng x\u00e9t\u00a0cho c\u00f9ng n\u00f3 c\u0169ng ch\u1ec9 l\u00e0 m\u1ed9t ph\u1ea7n c\u1ee7a cu\u1ed9c s\u1ed1ng v\u00e0 c\u1ea7n ph\u1ea3i \u0111\u01b0\u1ee3c \u0111\u00e1nh gi\u00e1, ki\u1ec3m so\u00e1t m\u1ed9t c\u00e1ch h\u1ee3p l\u00ed. Nh\u01b0ng \u0111\u1ec3 l\u00e0m \u0111\u01b0\u1ee3c t\u1ea5t c\u1ea3 nh\u1eefng \u0111i\u1ec1u n\u00e0y, ch\u00fang ta c\u1ea7n m\u1ed9t khu\u00f4n kh\u1ed5, m\u1ed9t s\u01a1 \u0111\u1ed3 t\u01b0 duy, v\u00e0 \u0111\u00f3 ch\u00ednh l\u00e0 \u0111i\u1ec1u m\u00e0 Kenneth \u0111em \u0111\u1ebfn trong cu\u1ed1n s\u00e1ch n\u00e0y. Anh c\u0169ng \u0111\u01b0a ra nhi\u1ec1u c\u00e2u h\u1ecfi m\u00e0 ch\u00fang ta ph\u1ea3i t\u1ef1 h\u1ecfi b\u1ea3n th\u00e2n m\u00ecnh. \u1ede cu\u1ed1i m\u1ed7i ch\u01b0\u01a1ng s\u1ebd c\u00f3 danh s\u00e1ch c\u00e1c c\u00e2u h\u1ecfi v\u00e0 ch\u00fang ta ph\u1ea3i suy ng\u1eabm \u0111\u1ec3 tr\u1ea3 l\u1eddi. V\u00ec v\u1eady, \u0111\u00e2y kh\u00f4ng ch\u1ec9 l\u00e0 m\u1ed9t cu\u1ed1n s\u00e1ch th\u00f4ng th\u01b0\u1eddng, n\u00f3 c\u00f2n l\u00e0 m\u1ed9t cu\u1ed1n s\u1ed5 l\u00e0m vi\u1ec7c thi\u1ebft th\u1ef1c, th\u0103m d\u00f2 v\u00e0 th\u00e1ch th\u1ee9c ta \u0111\u1ed1i di\u1ec7n v\u1edbi b\u1ea3n th\u00e2n \u0111\u1ec3 x\u00e1c \u0111\u1ecbnh \u0111\u01b0\u1ee3c n\u01a1i m\u00e0 ta th\u1eadt s\u1ef1 mu\u1ed1n \u0111\u1ebfn c\u0169ng nh\u01b0 c\u00e1ch m\u00e0 ta s\u1ebd \u0111i. T\u00f4i v\u00e0 Kenneth hi v\u1ecdng b\u1ea1n s\u1ebd c\u00f3 m\u1ed9t cu\u1ed9c h\u00e0nh tr\u00ecnh th\u00fa v\u1ecb v\u00e0 vi\u00ean m\u00e3n.", "img": "https://www.vinabook.com/images/thumbnails/product/240x/303599_p82483mbatrc.jpg", "author": "Kenneth Leow", "class": "kinhte", "name": "Hi\u1ec7n Th\u1ef1c H\u00f3a S\u1ef1 Nghi\u1ec7p (B\u00eca C\u1ee9ng)"}