{"publisher": "PandaBooks", "isbn": "8935077023213", "description": " H\u00e3y \u0111\u1eb7t m\u1ee5c ti\u00eau cao v\u00e0 sau \u0111\u00f3 b\u1ea1n s\u1ebd v\u01b0\u1ee3t qua nhi\u1ec1u kh\u00f3 kh\u0103n \u0111\u1ec3 \u0111\u1ea1t nh\u1eefng m\u1ee5c ti\u00eau \u0111\u00f3. Cu\u1ed1n s\u00e1ch n\u00e0y s\u1ebd gi\u00fap b\u1ea1n kinh doanh t\u1ed1t h\u01a1n, ki\u1ebfm \u0111\u01b0\u1ee3c nhi\u1ec1u ti\u1ec1n h\u01a1n, v\u00e0 \u0111i\u1ec1u quan tr\u1ecdng h\u01a1n c\u1ea3 l\u00e0 b\u1ea1n s\u1ebd th\u00e0nh \u0111\u1ea1t trong cu\u1ed9c s\u1ed1ng. Cu\u1ed1n s\u00e1ch cung c\u1ea5p cho b\u1ea1n ph\u01b0\u01a1ng ph\u00e1p \u0111\u1ec3 \u0111\u1ea1t \u0111\u01b0\u1ee3c nh\u1eefng m\u1ee5c \u0111\u00edch l\u1edbn trong c\u00f4ng vi\u1ec7c, trong c\u00e1c m\u1ed1i quan h\u1ec7 gia \u0111\u00ecnh, b\u1ea1n b\u00e8 v\u00e0 x\u00e3 h\u1ed9i. Kh\u00f4ng h\u1eb3n b\u1ea1n ph\u1ea3i l\u00e0 m\u1ed9t thi\u00ean t\u00e0i b\u1ea9m sinh \u0111\u1ec3 tr\u1edf n\u00ean m\u1ed9t ng\u01b0\u1eddi th\u00e0nh \u0111\u1ea1t, h\u00e0i l\u00f2ng v\u1edbi cu\u1ed9c s\u1ed1ng, nh\u01b0ng b\u1ea1n c\u1ea7n nh\u1eefng b\u00ed quy\u1ebft m\u00e0 cu\u1ed1n s\u00e1ch \u0111\u00e3 \u0111\u01b0a ra v\u00e0 ch\u1ec9 cho b\u1ea1n \u0111\u1ebfn n\u01a1i m\u00e0 b\u1ea1n mu\u1ed1n \u0111\u1ebfn: * H\u00e3y tin l\u00e0 b\u1ea1n th\u00e0nh c\u00f4ng v\u00e0 b\u1ea1n s\u1ebd th\u00e0nh c\u00f4ng. * T\u1ef1 c\u1ee9u tho\u00e1t m\u00ecnh kh\u1ecfi n\u1ed7i s\u1ee3 th\u1ea5t b\u1ea1i. * H\u00e3y c\u0169ng c\u1ed1 l\u00f2ng t\u1ef1 tin v\u00e0 ch\u1ea5m d\u1ee9t n\u1ed7i s\u1ee3 h\u00e3i. * H\u00e3y suy ngh\u0129 v\u00e0 \u01b0\u1edbc m\u01a1 m\u1ed9t c\u00e1ch s\u00e1ng t\u1ea1o. * T\u00ednh ch\u1ee7 \u0111\u1ed9ng l\u00e0 \u0111\u1ed3ng minh c\u1ee7a b\u1ea1n. * Bi\u1ebfn th\u00e1i \u0111\u1ed9 c\u1ee7a b\u1ea1n th\u00e0nh \u0111\u1ed3ng minh c\u1ee7a b\u1ea1n. * H\u1ecdc \u0111\u1ec3 tr\u1edf th\u00e0nh ng\u01b0\u1eddi suy ngh\u0129 l\u1ea1c quan. * H\u00e3y bi\u1ebfn th\u1ea5t b\u00e0i th\u00e0nh th\u1eafng l\u1ee3i. * D\u00f9ng m\u1ee5c \u0111\u00edch \u0111\u1ec3 gi\u00fap b\u1ea1n ti\u1ebfn l\u00ean. * H\u00e3y suy ngh\u0129 nh\u01b0 m\u1ed9t nh\u00e0 l\u00e3nh \u0111\u1ea1o. Trong cu\u1ed9c \u0111\u1eddi, ph\u1ea7n l\u1edbn m\u1ecdi ng\u01b0\u1eddi h\u00e0ng ng\u00e0y \u0111ang ph\u1ea3i tr\u1ea3i qua m\u1ed9t cu\u1ed9c s\u1ed1ng b\u00ecnh th\u01b0\u1eddng, m\u1eb7c d\u1ea7u c\u00f3 h\u00e0ng ng\u00e0n c\u01a1 h\u1ed9i \u0111\u1ec3 cho h\u1ecd th\u00e0nh c\u00f4ng trong hai th\u1eadp k\u1ef7 qua. V\u00e0 trong s\u1ef1 b\u00f9ng n\u1ed5 s\u1eafp t\u1edbi, s\u1ebd c\u00f3 nhi\u1ec1u ng\u01b0\u1eddi ph\u1ea3i lo l\u1eafng, t\u00ecm m\u1ecdi c\u00e1ch v\u01b0\u01a1n l\u00ean trong cu\u1ed9c s\u1ed1ng khi c\u1ea3m th\u1ea5y m\u00ecnh c\u00f2n th\u1ea5p k\u00e9m, thua xa m\u1ecdi ng\u01b0\u1eddi, kh\u00f4ng c\u00f3 kh\u1ea3 n\u0103ng l\u00e0m nh\u1eefng \u0111i\u1ec1u m\u00ecnh mu\u1ed1n, k\u1ebft qu\u1ea3 l\u00e0, h\u1ecd s\u1ebd ch\u1ec9 \u0111\u1ea1t \u0111\u01b0\u1ee3c m\u1ed9t ph\u1ea7n th\u01b0\u1edfng nh\u1ecf b\u00e9, m\u1ed9t h\u1ea1nh ph\u00fac b\u00e9 nh\u1ecf. C\u00f2n nh\u1eefng ng\u01b0\u1eddi bi\u1ebft bi\u1ebfn c\u01a1 h\u1ed9i th\u00e0nh ph\u1ea7n th\u01b0\u1edfng, h\u1ecd s\u1ebd th\u00e0nh c\u00f4ng. Hy v\u1ecdng r\u1eb1ng b\u1ea1n l\u00e0 m\u1ed9t trong m\u1ed9t s\u1ed1 nh\u1eefng ng\u01b0\u1eddi kh\u00f4n kh\u00e9o, bi\u1ebft n\u1eafm l\u1ea5y c\u01a1 h\u1ed9i v\u00e0 tr\u1edf th\u00e0nh ng\u01b0\u1eddi th\u00e0nh \u0111\u1ea1t. H\u00e3y b\u01b0\u1edbc v\u00e0o cu\u1ed9c s\u1ed1ng th\u1ef1c t\u1ebf \u0111i. C\u00e1nh c\u1eeda c\u1ee7a s\u1ef1 th\u00e0nh c\u00f4ng s\u1ebd m\u1edf r\u1ed9ng h\u01a1n l\u00fac n\u00e0o h\u1ebft. H\u00e3y gia nh\u1eadp c\u00e2u l\u1ea1c b\u1ed9 c\u1ee7a nh\u1eefng ng\u01b0\u1eddi th\u00e0nh \u0111\u1ea1t \u0111\u01b0\u1ee3c t\u1ea5t c\u1ea3 nh\u1eefng g\u00ec h\u1ecd mu\u1ed1n. \u0110\u00e2y l\u00e0 b\u01b0\u1edbc c\u01a1 b\u1ea3n \u0111\u1ea7u ti\u00ean \u0111\u1ec3 ti\u1ebfn t\u1edbi th\u00e0nh c\u00f4ng. M\u1ed9t b\u01b0\u1edbc l\u1edbn, kh\u00f4ng th\u1ec3 thi\u1ebfu \u0111\u01b0\u1ee3c \u0111\u00f3 l\u00e0: H\u00e3y t\u1ef1 tin v\u00e0o b\u1ea3n th\u00e2n! M\u1ee5c l\u1ee5c: Tin l\u00e0 th\u00e0nh c\u00f4ng v\u00e0 ch\u1eafc ch\u1eafn s\u1ebd th\u00e0nh c\u00f4ng Ch\u01b0\u01a1ng II: H\u00e3y xo\u00e1 \u0111i nh\u1eefng m\u1eb7c c\u1ea3m m\u1ea7m b\u1ec7nh c\u1ee7a m\u1ecdi th\u1ea5t b\u1ea1i Ch\u01b0\u01a1ng III: C\u1ee7ng c\u1ed1 ni\u1ec1m tin - Xua tan s\u1ef1 lo l\u1eafng s\u1ee3 h\u00e3i Ch\u01b0\u01a1ng IV: L\u00e0m th\u1ebf n\u00e0o \u0111\u1ec3 c\u00f3 t\u01b0 duy l\u1edbn Ch\u01b0\u01a1ng V: L\u00e0m th\u1ebf n\u00e0o \u0111\u1ec3 s\u00e1ng t\u1ea1o nhi\u1ec1u h\u01a1n Ch\u01b0\u01a1ng VI: B\u1ea1n ngh\u0129 m\u00ecnh l\u00e0 ng\u01b0\u1eddi nh\u01b0 th\u1ebf n\u00e0o? B\u1ea1n s\u1ebd l\u00e0 ng\u01b0\u1eddi nh\u01b0 v\u1eady Ch\u01b0\u01a1ng VII: H\u00e3y \u0111i\u1ec1u khi\u1ec3n m\u00f4i tr\u01b0\u1eddng xung quanh Ch\u01b0\u01a1ng VIII: Bi\u1ebfn th\u00e1i \u0111\u1ed9 c\u1ee7a b\u1ea1n th\u00e0nh \u0111\u1ed3ng minh c\u1ee7a b\u1ea1n Ch\u01b0\u01a1ng IX: H\u00e3y ngh\u0129 \u0111\u00fang v\u1ec1 ng\u01b0\u1eddi kh\u00e1c Ch\u01b0\u01a1ng X: H\u00ecnh th\u00e0nh th\u00f3i quen h\u00e0nh \u0111\u1ed9ng Ch\u01b0\u01a1ng XI: L\u00e0m th\u1ebf n\u00e0o \u0111\u1ec3 chuy\u1ec3n th\u1ea5t b\u1ea1i th\u00e0nh chi\u1ebfn th\u1eafng Ch\u01b0\u01a1ng XII: \u0110\u1eb7t m\u1ee5c ti\u00eau cho m\u00ecnh \u0111\u1ec3 v\u01b0\u01a1n l\u00ean Ch\u01b0\u01a1ng XIII: L\u00e0m th\u1ebf n\u00e0o \u0111\u1ec3 suy ngh\u0129 gi\u1ed1ng nh\u01b0 m\u1ed9t nh\u00e0 l\u00e3nh \u0111\u1ea1o M\u1eddi b\u1ea1n \u0111\u00f3n \u0111\u1ecdc.", "img": "https://www.vinabook.com/images/thumbnails/product/240x/26367_32836.jpg", "author": "\u0110\u1ee9c Minh", "class": "phattrienbanthan", "name": "B\u00ed Quy\u1ebft Th\u00e0nh \u0110\u1ea1t Trong \u0110\u1eddi Ng\u01b0\u1eddi - Con \u0111\u01b0\u1eddng D\u1eabn \u0110\u1ebfn Th\u00e0nh \u0110\u1ea1t V\u00e0 Danh Ti\u1ebfng"}