{"publisher": "\u0110inh T\u1ecb", "isbn": "8935077003451", "description": " M\u1ee5c l\u1ee5c:  Ph\u1ea7n 1: Nghi\u00ean c\u1ee9u - ti\u1ec3u lu\u1eadn. S\u1ef1 ra \u0111\u1eddi c\u1ee7a b\u00e1o Vi\u1ec7t Nam \u0111\u1ed9c l\u1eadp. \"V\u01b0\u1eddn v\u0103n\" gi\u00e0u h\u01b0\u01a1ng s\u1eafc tr\u00ean b\u00e1o Vi\u1ec7t Nam \u0111\u1ed9c l\u1eadp. Nh\u1eefng v\u1ea7n th\u01a1 l\u1ebb tr\u00ean b\u00e1o Vi\u1ec7t Nam \u0111\u1ed9c l\u1eadp. Kh\u00ed th\u1ebf kh\u1edfi ngh\u0129a qua nh\u1eefng v\u1ea7n th\u01a1 tr\u00ean b\u00e1o Vi\u1ec7t Nam \u0111\u1ed9c l\u1eadp. Ph\u1ea7n 2: S\u01b0u t\u1eadp - tuy\u1ec3n ch\u1ecdn. Th\u01a1 ca n\u0103m 1941. Th\u01a1 ca n\u0103m 1942. Th\u01a1 ca n\u0103m 1943. Th\u01a1 ca n\u0103m 1944. Th\u01a1 ca n\u0103m 1945. M\u1eddi b\u1ea1n \u0111\u00f3n \u0111\u1ecdc.  \u00a0", "img": "https://www.vinabook.com/images/thumbnails/product/240x/30776_37298.jpg", "author": "V\u0169 Ch\u00e2u Qu\u00e1n", "class": "vanhoc", "name": "B\u00e1c H\u1ed3 V\u1edbi B\u00e1o Vi\u1ec7t Nam \u0110\u1ed9c L\u1eadp"}