{"publisher": "Alpha books", "isbn": "8936037748160", "description": " \"M\u1ed1i t\u00ecnh \u0111\u1ea7u c\u1ee7a t\u00f4i l\u00e0 b\u1ea1n Long. N\u0103m \u0111\u1ea7u ti\u00ean khi t\u00f4i \u0111i h\u1ecdc M\u1eabu gi\u00e1o, th\u00ec b\u1ea1n h\u1ecdc kh\u00e1c l\u1edbp t\u00f4i. Ch\u00fang t\u00f4i ch\u1ec9 ch\u01a1i chung v\u00e0o gi\u1edd ra ch\u01a1i th\u00f4i. Ch\u00fang t\u00f4i r\u1ea5t y\u00eau qu\u00ed nhau v\u00e0 th\u1eadt tuy\u1ec7t v\u00ec n\u0103m sau b\u1ea1n \u0111\u00e3 chuy\u1ec3n sang h\u1ecdc l\u1edbp t\u00f4i. L\u00fd do kh\u00f4ng ph\u1ea3i v\u00ec t\u00f4i \u0111\u00e2u  m\u00e0 v\u00ec b\u1ea1n \u0103n c\u01a1m r\u1ea5t ch\u1eadm v\u00e0 \u00edt n\u1eefa, trong khi c\u00f4 gi\u00e1o ch\u1ee7 nhi\u1ec7m l\u1edbp t\u00f4i l\u00e0 ng\u01b0\u1eddi b\u00f3n c\u01a1m gi\u1ecfi nh\u1ea5t tr\u01b0\u1eddng.\" \"\u0110\u00e1nh nhau v\u1edbi anh h\u1ecd t\u00f4i l\u00e0 vi\u1ec7c t\u00f4i lu\u00f4n r\u1ea5t s\u1eb5n l\u00f2ng. \u0110\u01a1n gi\u1ea3n v\u00ec t\u00f4i b\u00e9o v\u00e0 anh th\u00ec g\u1ea7y v\u00e0 b\u00e9 kh\u1ee7ng khi\u1ebfp. Anh kh\u00f4ng c\u00f3 nhi\u1ec1u kh\u1ea3 n\u0103ng chi\u1ebfn th\u1eafng. T\u00f4i th\u1eafng th\u00ec d\u0129 nhi\u00ean anh ph\u1ea3i m\u1ea5t c\u1ea3 h\u1ed9p bi cho t\u00f4i r\u1ed3i. M\u00e0 n\u1ebfu anh c\u00f3 th\u1eafng th\u00ec t\u00f4i s\u1ebd l\u1ea1i kh\u00f3c g\u00e0o l\u00ean v\u00e0 ch\u1ea1y \u0111i m\u00e1ch b\u00e0 r\u1eb1ng anh \u0111\u00e3 l\u00e0m nh\u00e0u truy\u1ec7n c\u1ee7a t\u00f4i l\u1ea1i c\u00f2n \u0111\u00e1nh t\u00f4i. T\u00f3m l\u1ea1i, \u0111\u00e1nh nhau v\u1edbi anh l\u00e0 m\u1ed9t vi\u1ec7c m\u00e0 ki\u1ec3u g\u00ec t\u00f4i c\u0169ng kh\u00f4ng th\u1ec3 thi\u1ec7t \u0111\u01b0\u1ee3c.\" M\u1eddi b\u1ea1n \u0111\u00f3n \u0111\u1ecdc.", "img": "https://www.vinabook.com/images/thumbnails/product/240x/35048_41591.jpg", "author": "B\u1ea1ch Ng\u1ecdc Hoa", "class": "vanhoc", "name": "Tr\u1ebb Con Ph\u1ed1 H\u00e0ng"}