{"publisher": "Ph\u01b0\u01a1ng \u0110\u00f4ng", "isbn": "8936047861002", "description": " \"Ph\u1ee5 n\u1eef trong v\u0103n S\u01b0\u01a1ng Nguy\u1ec7t Minh th\u01b0\u1eddng \u0111\u1eb9p... T\u00e1c gi\u1ea3 y\u00eau c\u00e1i \u0111\u1eb9p, ch\u0103m ch\u00fat n\u00f3 v\u1edbi t\u1ea5t c\u1ea3 c\u00e1c m\u1ef9 t\u1eeb c\u00f3 th\u1ec3. \u0110\u00f4i l\u00fac ng\u01b0\u1eddi \u0111\u1ecdc c\u00f3 c\u1ea3m gi\u00e1c nh\u01b0 ch\u1ea1m tay v\u00e0o l\u00e0 v\u1ebb \u0111\u1eb9p \u1ea5y tan \u0111i, ho\u1eb7c th\u00eam m\u1ed9t b\u01b0\u1edbc, th\u00eam m\u1ed9t h\u01a1i th\u1edf l\u00e0 n\u00f3 lo\u00e3ng ra c\u00f9ng kh\u00f4ng kh\u00ed\" M\u1ee5c l\u1ee5c M\u1eddi b\u1ea1n \u0111\u00f3n \u0111\u1ecdc", "img": "https://www.vinabook.com/images/thumbnails/product/240x/38356_44899.jpg", "author": "S\u01b0\u01a1ng Nguy\u1ec7t Minh", "class": "vanhoc", "name": "\u0110\u00eam Th\u00e1nh V\u00f4 C\u00f9ng"}