{"publisher": "Ph\u01b0\u01a1ng \u0110\u00f4ng", "isbn": "8936047861989", "description": " Trong T\u00f9 Ngo\u00e0i T\u1ed9i - Ph\u1ea7n 1 Cu\u1ed1n s\u00e1ch \"Trong T\u00f9 Ngo\u00e0i T\u1ed9i\" l\u00e0 nh\u1eefng ghi ch\u00e9p \u0111\u1eabm m\u00e1u v\u00e0 n\u01b0\u1edbc m\u1eaft c\u1ee7a nh\u00e0 v\u0103n Nguy\u1ec5n \u0110\u00ecnh T\u00fa, t\u00e1c gi\u1ea3 c\u00e1c ti\u1ec3u thuy\u1ebft n\u1ed5i ti\u1ebfng: H\u1ed3 s\u01a1 m\u1ed9t t\u1eed t\u00f9, Nh\u00e1p, Phi\u00ean b\u1ea3n, K\u00edn. M\u1ee5c l\u1ee5c: ...  M\u1eddi b\u1ea1n \u0111\u00f3n \u0111\u1ecdc.", "img": "https://www.vinabook.com/images/thumbnails/product/240x/43890_50433.jpg", "author": "Nguy\u1ec5n \u0110\u00ecnh T\u00fa", "class": "vanhoc", "name": "Trong T\u00f9 Ngo\u00e0i T\u1ed9i - Ph\u1ea7n 1"}