{"publisher": "NXB Tr\u1ebb", "isbn": "8934974142034", "description": " M\u1ed9t t\u1eadp truy\u1ec7n ng\u1eafn nh\u1eb9 nh\u00e0ng, dung d\u1ecb v\u00e0 c\u1ea3m \u0111\u1ed9ng. M\u1ed7i c\u00e2u chuy\u1ec7n l\u00e0 m\u1ed9t l\u00e1t c\u1eaft s\u1ed1 ph\u1eadn \u00e9o le nh\u01b0ng lu\u00f4n \u0111\u01b0\u1ee3c ng\u01b0\u1eddi k\u1ec3 nh\u00ecn b\u1eb1ng \u00e1nh m\u1eaft nh\u00e2n v\u0103n, \u1ea5m \u00e1p.\u00a0 M\u1eddi b\u1ea1n \u0111\u00f3n \u0111\u1ecdc.", "img": "https://www.vinabook.com/images/thumbnails/product/240x/223504_p70067mbt.jpg", "author": "Tr\u01b0\u01a1ng V\u0103n Tu\u1ea5n", "class": "vanhoc", "name": "M\u00e2y Tr\u1eafng Gi\u0103ng Ngang L\u01b0ng \u0110\u1ed3i"}