{"publisher": "Ph\u01b0\u01a1ng Nam", "isbn": "8932000122173", "description": " Th\u01b0 G\u1edfi Ng\u01b0\u1eddi B\u1eadn R\u1ed9n t\u1eadp h\u1ee3p h\u01a1n 60 b\u1ee9c th\u01b0 g\u1eedi \u0111\u1ed9c gi\u1ea3 b\u00e1o Doanh nh\u00e2n S\u00e0i G\u00f2n cu\u1ed1i tu\u1ea7n. M\u1ed7i b\u1ee9c th\u01b0 l\u00e0 l\u1eddi tr\u00f2 chuy\u1ec7n c\u1ee7a b\u00e1c s\u0129 \u0110\u1ed7 H\u1ed3ng Ng\u1ecdc v\u1ec1 c\u00e1c v\u1ea5n \u0111\u1ec1 trong cu\u1ed9c s\u1ed1ng nh\u01b0: d\u00e0nh th\u1eddi gi\u1edd cho ch\u00ednh m\u00ecnh v\u00e0 ng\u01b0\u1eddi m\u00ecnh th\u01b0\u01a1ng y\u00eau, chuy\u1ec7n nh\u00e2n b\u1ea3n v\u00f4 t\u00ednh, chuy\u1ec7n \u0103n u\u1ed1ng v\u00e0 thu\u1ed1c men... v\u1edbi gi\u1ecdng v\u0103n d\u00ed d\u1ecfm, gi\u00e0u c\u1ea3m x\u00fac \u0111an xen nhi\u1ec1u ki\u1ebfn th\u1ee9c y khoa c\u1ee7a \u0110\u00f4ng - T\u00e2y. M\u1eddi b\u1ea1n \u0111\u00f3n \u0111\u1ecdc.", "img": "https://www.vinabook.com/images/thumbnails/product/240x/230773_p71224m001.jpg", "author": "\u0110\u1ed7 H\u1ed3ng Ng\u1ecdc", "class": "vanhoc", "name": "Th\u01b0 G\u1edfi Ng\u01b0\u1eddi B\u1eadn R\u1ed9n - T\u1eadp 1 (T\u00e1i B\u1ea3n 2016)"}