{"publisher": "NXB Tr\u1ebb", "isbn": "8934974090557", "description": " S\u00e1ch l\u00e0 s\u1ef1 tr\u1ea3i nghi\u1ec7m c\u1ee7a nh\u1eefng ng\u01b0\u1eddi s\u1ed1ng c\u00f9ng m\u1ed9t m\u00e1i nh\u00e0: cha v\u00e0 m\u1eb9, anh v\u00e0 em, \u00f4ng b\u00e0 v\u00e0 ch\u00e1u\u2026 B\u1ea1n s\u1ebd \u0111\u01b0\u1ee3c phi\u00eau du trong m\u1ed9t th\u1ebf gi\u1edbi th\u00e2n thu\u1ed9c nh\u01b0ng c\u0169ng \u0111\u1ea7y l\u00fd th\u00fa, n\u01a1i m\u00e0 m\u1ed1i d\u00e2y r\u00e0ng bu\u1ed9c gi\u1eefa c\u00e1c th\u00e0nh vi\u00ean d\u01b0\u1ee3c x\u00e2y d\u1ef1ng b\u1edfi th\u1ee9 t\u00ecnh c\u1ea3m ru\u1ed9t th\u1ecbt g\u1eafn b\u00f3. S\u1ef1 \u0111\u1ed3ng c\u1ea3m t\u1ef1 nhi\u00ean m\u00e0 b\u1ec1n v\u1eefng \u0111\u00f3 c\u0169ng l\u00e0 nh\u1eefng ph\u00e9p m\u00e0u thi\u00eang li\u00eang n\u00e2ng cao b\u01b0\u1edbc ch\u00e2n m\u1ed7i khi ta ch\u00f9n b\u01b0\u1edbc. M\u1eddi b\u1ea1n \u0111\u00f3n \u0111\u1ecdc. ", "img": "https://www.vinabook.com/images/thumbnails/product/240x/30415_36937.jpg", "author": "Nhi\u1ec1u T\u00e1c Gi\u1ea3", "class": "phattrienbanthan", "name": "L\u1eddi Mu\u1ed1n N\u00f3i - Ph\u00e9p M\u00e0u N\u1ed1i Nh\u1eefng Tr\u00e1i Tim - T\u00e1i b\u1ea3n 09/09/2009"}