{"publisher": "Tr\u00ed Vi\u1ec7t", "isbn": "8935086824726", "description": "  Cu\u00f4\u0323c s\u00f4\u0301ng c\u00f3 nhi\u00ea\u0300u \u0111i\u00ea\u0300u khi\u00ea\u0301n ta ph\u1ea3i b\u00e2\u0323n t\u00e2m v\u00e0 lo l\u1eafng. Lo l\u1eafng l\u00e0 \u0111i\u00ea\u0300u ho\u00e0n to\u00e0n b\u00ecnh th\u01b0\u1eddng, nh\u01b0ng n\u00ea\u0301u kh\u00f4ng bi\u00ea\u0301t ki\u00ea\u0309m so\u00e1t v\u00e0 li\u00ean t\u1ee5c nu\u00f4ng chi\u00ea\u0300u d\u1ea1ng c\u1ea3m x\u00fac n\u00e0y, ch\u00fang ta s\u1ebd t\u1ef1 \u0111\u00e1nh m\u00e2\u0301t t\u1eebng ng\u00e0y qu\u00fd gi\u00e1 c\u1ee7a m\u00ecnh. Th\u00f4ng quaD\u00f9 b\u00e2\u0301t k\u1ef3 \u0111i\u00ea\u0300u g\u00ec x\u1ea3y ra...,\u00a0b\u00e1c s\u0129 t\u00e2m l\u00fd\u00a0A.J.Chevalier\u00a0s\u1ebd gi\u00fap ta ch\u00ea\u0301 ng\u1ef1 c\u1ea3m gi\u00e1c lo l\u1eafng, v\u00e2\u0323n d\u1ee5ng s\u1ee9c m\u1ea1nh n\u00f4\u0323i t\u1ea1i c\u1ee7a b\u1ea3n th\u00e2n \u0111\u00ea\u0309 nh\u00e2\u0323n \u0111\u1ecbnh r\u00f5 \u0111\u00e2u l\u00e0 nh\u1eefng b\u0103n kho\u0103n c\u00e2\u0300n thi\u00ea\u0301t, \u0111\u00e2u l\u00e0 nh\u1eefng b\u00e2\u0301t an c\u00f3 th\u00ea\u0309 lo\u1ea1i b\u1ecf. Ta s\u1ebd bi\u00ea\u0301t c\u00e1ch bi\u00ea\u0301n t\u00e2m tr\u1ea1ng lo l\u1eafng th\u00e0nh nh\u1eefng h\u00e0nh vi t\u00edch c\u1ef1c, h\u1ecdc \u0111\u01b0\u1ee3c c\u00e1ch \u0111\u00f4\u0301i \u0111\u00e2\u0300u v\u1edbi c\u0103ng th\u1eb3ng v\u00e0 nh\u00e2\u0323n ra \u00fd ngh\u0129a \u0111\u1eb1ng sau nh\u1eefng \u0111i\u00ea\u0300u khi\u00ea\u0301n ta lo l\u1eafng, \u0111\u00f3 ch\u00ednh l\u00e0 c\u01a1 h\u00f4\u0323i \u0111\u00ea\u0309 ta c\u00f3 nh\u1eefng thay \u0111\u00f4\u0309i t\u00edch c\u1ef1c v\u00e0 tr\u01b0\u1edfng th\u00e0nh. M\u1eddi b\u1ea1n \u0111\u00f3n \u0111\u1ecdc.", "img": "https://www.vinabook.com/images/thumbnails/product/240x/47013_53556.jpg", "author": "A.J.Chevalier", "class": "phattrienbanthan", "name": "D\u00f9 B\u1ea5t K\u1ef3 \u0110i\u1ec1u G\u00ec X\u1ea3y Ra..."}