{"publisher": "V\u0103n Lang", "isbn": "8935074108524", "description": "  \u0110\u1ec3 th\u00e0nh c\u00f4ng trong cu\u1ed9c s\u1ed1ng, b\u1ea1n c\u1ea7n r\u1ea5t nhi\u1ec1u th\u1ee9: m\u1ee5c ti\u00eau \u0111\u00fang \u0111\u1eafn, \u00fd ch\u00ed m\u1ea1nh m\u1ebd, n\u0103ng l\u1ef1c chuy\u00ean m\u00f4n\u2026 nh\u01b0ng kh\u00f4ng th\u1ec3 thi\u1ebfu m\u1ed9t c\u00f4ng c\u1ee5 v\u00f4 c\u00f9ng h\u1eefu hi\u1ec7u c\u00f3 th\u1ec3 gi\u00fap b\u1ea1n v\u01b0\u1ee3t qua nh\u1eefng tr\u1edf ng\u1ea1i khi giao ti\u1ebfp v\u00e0 x\u1eed l\u00fd c\u00e1c m\u1ed1i quan h\u1ec7 x\u00e3 h\u1ed9i, \u0111\u00f3 l\u00e0 thu\u1eadt n\u00f3i chuy\u1ec7n. Con ng\u01b0\u1eddi l\u00e0 m\u1ed9t th\u1ef1c th\u1ec3 x\u00e3 h\u1ed9i. Ch\u00fang ta s\u1ed1ng trong c\u1ed9ng \u0111\u1ed3ng v\u00e0 m\u1ecdi th\u00e0nh c\u00f4ng hay th\u1ea5t b\u1ea1i c\u1ee7a ch\u00fang ta c\u0169ng kh\u1edfi \u0111\u1ea7u v\u00e0 k\u1ebft th\u00fac trong \u0111\u1eddi s\u1ed1ng c\u1ed9ng \u0111\u1ed3ng, do \u0111\u00f3, ngh\u1ec7 thu\u1eadt giao t\u1ebf c\u00f3 vai tr\u00f2 h\u1ebft s\u1ee9c quan tr\u1ecdng \u0111\u1ed1i v\u1edbi s\u1ef1 nghi\u1ec7p c\u0169ng nh\u01b0 h\u1ea1nh ph\u00fac c\u1ee7a b\u1ea5t k\u1ef3 ai. B\u1ea1n c\u00f3 th\u1ec3 th\u00e0nh c\u00f4ng nh\u1edd nh\u1eefng ph\u1ea9m ch\u1ea5t \u01b0u t\u00fa c\u00e1 nh\u00e2n, nh\u01b0ng c\u0169ng c\u00f3 th\u1ec3 th\u1ea5t b\u1ea1i ch\u1ec9 v\u00ec kh\u00f4ng bi\u1ebft l\u00e0m c\u00e1ch n\u00e0o \u0111\u1ec3 nh\u1eefng ph\u1ea9m ch\u1ea5t \u1ea5y t\u1ecfa s\u00e1ng trong \u0111\u1eddi s\u1ed1ng h\u00e0ng ng\u00e0y. S\u00e1ch Thu\u1eadt n\u00f3i chuy\u1ec7n s\u1ebd gi\u00fap b\u1ea1n kh\u1eafc ph\u1ee5c tr\u1edf ng\u1ea1i \u0111\u00f3, h\u01a1n n\u1eefa, c\u00f2n gia t\u0103ng g\u1ea5p b\u1ed9i nh\u1eefng \u1ea3nh h\u01b0\u1edfng t\u1ed1t \u0111\u1eb9p c\u1ee7a b\u1ea1n trong v\u00f9ng c\u1ed9ng h\u01b0\u1edfng c\u1ee7a truy\u1ec1n th\u00f4ng.nh\u00e0 s\u00e1ch online M\u1ecdi b\u00ed quy\u1ebft \u0111\u1ec3 b\u1ea1n th\u00e0nh c\u00f4ng \u0111\u1ec1u c\u00f3 trong cu\u1ed1n s\u00e1ch n\u00e0y.", "img": "https://www.vinabook.com/images/thumbnails/product/240x/218143_p69357mbt.jpg", "author": "T\u00f4 Minh", "class": "phattrienbanthan", "name": "Thu\u1eadt N\u00f3i Chuy\u1ec7n (T\u00e1i B\u1ea3n 2016)"}