{"publisher": "Tr\u00ed Vi\u1ec7t", "isbn": "8935086841570", "description": "  \u201cCu\u1ed9c s\u1ed1ng v\u1ed1n v\u00f4 t\u01b0, c\u1edfi m\u1edf v\u00e0 kh\u00f4ng thi\u00ean v\u1ecb. Ta ngh\u0129 \u0111\u1eddi th\u1ebf n\u00e0o th\u00ec \u0111\u1eddi l\u00e0 th\u1ebf \u1ea5y. C\u00f3 ng\u01b0\u1eddi th\u1ea5y \u0111\u1eddi vui v\u00e0 \u0111\u1eb9p, c\u00f3 k\u1ebb l\u1ea1i cho \u0111\u1eddi \u0111au bu\u1ed3n, t\u00e0n \u00e1c. Ng\u01b0\u1eddi n\u00e0o c\u0169ng c\u00f3 l\u00fd do ri\u00eang \u0111\u1ec3 c\u1ea3m nh\u1eadn \u0111\u1eddi theo c\u00e1ch c\u1ee7a m\u00ecnh...\u201d 15 c\u00e2u chuy\u1ec7n v\u1edbi r\u1ea5t nhi\u1ec1u nh\u00e2n v\u1eadt nh\u01b0ng kh\u00f4ng c\u00f3 ai tr\u00f2n \u0111\u1ea7y v\u00e0 kh\u00f4ng c\u00f3 c\u00e1i g\u00ec tr\u00f2n \u0111\u1ea7y c\u1ea3. C\u00f3 s\u1ef1 thi\u1ebfu v\u1eafng n\u00e0o \u0111\u1ea5y b\u00ean trong ph\u1ea7n th\u1ea5y \u0111\u01b0\u1ee3c c\u1ee7a con ng\u01b0\u1eddi, c\u1ea3 \u1edf ph\u1ea7n kh\u00f4ng th\u1ea5y \u0111\u01b0\u1ee3c, v\u00e0 kh\u00f4ng ch\u1ec9 trong con ng\u01b0\u1eddi m\u00e0 ngay c\u1ea3 trong kh\u00f4ng gian, trong mu\u00f4ng th\u00fa, c\u00e2y c\u1ecf... M\u1ed7i c\u00e2u chuy\u1ec7n trong cu\u1ed1n H\u1ea1t Gi\u1ed1ng T\u00e2m H\u1ed3n - Nh\u1eefng T\u00e2m H\u1ed3n L\u1ea1c l\u00e0 nh\u1eefng kh\u00fac ca bu\u1ed3n v\u1ec1 t\u00ecnh y\u00eau v\u00e0 th\u00e2n ph\u1eadn con ng\u01b0\u1eddi trong cu\u1ed9c s\u1ed1ng hi\u1ec7n \u0111\u1ea1i \u0111\u1ea7y bi\u1ebfn \u0111\u1ed9ng. Trong kh\u00fac ca bu\u1ed3n \u0111\u00f3 l\u00e0 nh\u1eefng t\u00e2m tr\u1ea1ng ng\u1ed5n ngang, nh\u1eefng khao kh\u00e1t \u0111\u01b0\u1ee3c y\u00eau v\u00e0 \u0111\u01b0\u1ee3c s\u1ed1ng m\u1ed9t c\u00e1ch \u0111\u00fang ngh\u0129a, nh\u1eefng d\u1eb1n v\u1eb7t v\u1ec1 tinh th\u1ea7n v\u00e0 ti\u1ec1n b\u1ea1c, nh\u1eefng kho\u1ea3ng tr\u1ed1ng bao la c\u1ea7n \u0111\u01b0\u1ee3c l\u1ea5p \u0111\u1ea7y\u2026 t\u1ea5t c\u1ea3 \u0111\u00e3 \u0111\u01b0\u1ee3c ph\u00f4 b\u00e0y m\u1ed9t c\u00e1ch r\u00e0nh m\u1ea1ch v\u00e0 s\u00f2ng ph\u1eb3ng trong cu\u1ed1n s\u00e1ch Nh\u1eefng T\u00e2m H\u1ed3n L\u1ea1c. \u0110\u1eb1ng sau \u0111\u00f3, ng\u01b0\u1eddi \u0111\u1ecdc d\u1ec5 d\u00e0ng nh\u1eadn ra nh\u1eefng c\u00e1i nh\u00ecn \u0111\u1ea7y nh\u00e2n b\u1ea3n v\u00e0 bao dung c\u1ee7a t\u00e1c gi\u1ea3 d\u00e0nh cho nh\u1eefng linh h\u1ed3n kh\u00f4ng \u0111\u01b0\u1ee3c b\u00ecnh th\u01b0\u1eddng \u1ea5y trong x\u00e3 h\u1ed9i. Nh\u1eefng t\u00ecnh y\u00eau v\u00e0 th\u00e2n ph\u1eadn trong cu\u1ed1n s\u00e1ch Nh\u1eefng T\u00e2m H\u1ed3n L\u1ea1c nh\u01b0 xa x\u00f4i, nh\u01b0 g\u1ea7n g\u0169i v\u00e0 \u0111\u00e2u \u0111\u00f3 c\u00f3 \u0111\u00f4i l\u1ea7n ta \u0111\u00e3 g\u1eb7p, \u0111\u00e3 th\u1ea5y v\u00e0 v\u00f4 t\u00ecnh l\u01b0\u1edbt qua.", "img": "https://www.vinabook.com/images/thumbnails/product/240x/255724_p75508m002.jpg", "author": "Nhi\u1ec1u T\u00e1c Gi\u1ea3", "class": "phattrienbanthan", "name": "H\u1ea1t Gi\u1ed1ng T\u00e2m H\u1ed3n - Nh\u1eefng T\u00e2m H\u1ed3n L\u1ea1c (T\u00e1i B\u1ea3n 2016)"}