{"publisher": "NXB Ph\u1ee5 N\u1eef", "isbn": "9786045609415", "description": " \"...Nh\u00e0 ph\u00ea b\u00ecnh kh\u00f4ng l\u00e0m \u0111\u01b0\u1ee3c c\u00f4ng vi\u1ec7c c\u1ee7a nh\u00e0 v\u0103n, nh\u01b0ng anh c\u00f3 \u0111i\u1ec1u ki\u1ec7n \u0111\u1ec3 t\u1ec9nh t\u00e1o h\u01a1n - t\u1ea5t nhi\u00ean n\u1ebfu qu\u1ea3 anh c\u00f3 t\u00e0i. V\u00e0 khi anh \u0111\u1ecdc \u0111\u01b0\u1ee3c c\u00e1i t\u1ea1ng c\u1ee7a nh\u00e0 v\u0103n, th\u00ec anh s\u1ebd g\u1ecdi \u0111\u01b0\u1ee3c cho nh\u00e0 v\u0103n suy ngh\u0129 v\u1ec1 ch\u00ednh m\u00ecnh, t\u1ec9nh t\u00e1o h\u01a1n, \u0111i\u1ec1u ng\u01b0\u1eddi \u0111ang s\u00e1ng t\u1ea1o th\u01b0\u1eddng kh\u00f3 v\u00ec \u0111ang m\u1ea3i \u0111am m\u00ea. Ng\u01b0\u1eddi \u0111ang s\u00e1ng t\u1ea1o c\u00f3 c\u00e1i g\u00ec \u0111\u00f3 gi\u1ed1ng nh\u01b0 ng\u01b0\u1eddi say r\u01b0\u1ee3u v\u1eady; l\u00fac \u0111\u00f3 m\u00e0 h\u1ecd t\u1ec9nh th\u00ec th\u01b0\u1eddng ch\u1eb3ng ra g\u00ec. Ng\u01b0\u1eddi ph\u00ea b\u00ecnh \u1edf b\u00ean c\u1ea1nh, \u00e2n c\u1ea7n, tinh t\u1ebf, ch\u0103m ch\u00fa \u0111\u1ecdc. \u0110\u1ecdc m\u1ed9t t\u00e2m h\u1ed3n, m\u1ed9t gi\u1ecdng \u0111i\u1ec7u t\u00e2m h\u1ed3n. V\u00e0 l\u1ea7n ra c\u00e1i t\u00f4i g\u1ecdi l\u00e0 c\u00e1i t\u1ea1ng. Theo ngh\u0129a \u0111\u00f3, anh l\u00e0 ng\u01b0\u1eddi b\u1ea1n t\u00e2m \u0111\u1eafc c\u1ee7a nh\u00e0 v\u0103n. T\u00f4i ngh\u0129 t\u00f4i t\u00ecm th\u1ea5y \u0111\u01b0\u1ee3c m\u1ed9t ng\u01b0\u1eddi b\u1ea1n nh\u01b0 v\u1eady \u1edf Nguy\u1ec5n \u0110\u0103ng M\u1ea1nh\" Nguy\u00ean Ng\u1ecdc \"V\u0103n h\u1ecdc hi\u1ec7n \u0111\u1ea1i Vi\u1ec7t Nam l\u00e0 m\u1ed9t n\u1ec1n v\u0103n h\u1ecdc phong ph\u00fa, kh\u00f4ng thi\u1ebfu nh\u1eefng t\u00e0i n\u0103ng \u0111\u1ed9c \u0111\u00e1o...,nh\u1eefng ng\u01b0\u1eddi l\u00e0m ra n\u1ec1n v\u0103n h\u1ecdc n\u00e0y l\u00e0 nh\u1eefng nh\u00e2n c\u00e1ch h\u1ea5p d\u1eabn, nh\u1eefng b\u1ed9 m\u1eb7t \u0111\u00e1ng y\u00eau, nh\u1eefng t\u00e0i n\u0103ng \u0111\u00e1ng tr\u00e2n tr\u1ecdng, th\u1ebf gi\u1edbi ngh\u1ec7 thu\u1eadt c\u1ee7a h\u1ecd kh\u00f4ng \u0111\u01a1n gi\u1ea3n[...]. T\u00e1i hi\u1ec7n th\u1ebf gi\u1edbi ngh\u1ec7 thu\u1eadt c\u1ee7a h\u1ecd, Nguy\u1ec5n \u0110\u0103ng M\u1ea1nh \u0111\u00e3 vi\u1ebft nh\u1eefng trang v\u0103n hay, nh\u1eefng trang th\u1ef1c s\u1ef1 l\u00e0 v\u0103n ch\u01b0\u01a1ng, ch\u1ee9ng t\u1ecf r\u1eb1ng ng\u01b0\u1eddi vi\u1ebft c\u0169ng l\u00e0 m\u1ed9t t\u00e0i n\u0103ng v\u0103n h\u1ecdc.\" Ho\u00e0ng Ng\u1ecdc Hi\u1ebfn M\u1eddi b\u1ea1n \u0111\u00f3n \u0111\u1ecdc.", "img": "https://www.vinabook.com/images/thumbnails/product/240x/41831_48374.jpg", "author": "Nguy\u1ec5n \u0110\u0103ng M\u1ea1nh", "class": "vanhoc", "name": "V\u0103n H\u1ecdc Vi\u1ec7t Nam Hi\u1ec7n \u0110\u1ea1i - Nh\u1eefng G\u01b0\u01a1ng M\u1eb7t Ti\u00eau Bi\u1ec3u"}