{"publisher": "NXB Tr\u1ebb", "isbn": "8934974116141", "description": " N\u00e9t B\u00fat Tri \u00c2n - T\u1eadp 3: Th\u1eafp L\u1eeda Y\u00eau Th\u01b0\u01a1ng \"N\u00e9t b\u00fat tri \u00e2n\" t\u1eadp 3 t\u1eadp h\u1ee3p nh\u1eefng c\u00e2u chuy\u1ec7n vi\u1ebft b\u1edfi tr\u00e1i tim ch\u1ea1m \u0111\u1ebfn tr\u00e1i tim ng\u01b0\u1eddi \u0111\u1ecdc, l\u00e0m ch\u00fang ta c\u00e0ng th\u00eam tin y\u00eau cu\u1ed9c s\u1ed1ng, tin v\u00e0o nh\u1eefng gi\u00e1 tr\u1ecb t\u1ed1t \u0111\u1eb9p c\u1ee7a truy\u1ec1n th\u1ed1ng d\u00e2n t\u1ed9c Vi\u1ec7t Nam. V\u1edbi th\u00f4ng \u0111i\u1ec7p \"Chia s\u1ebb l\u00f2ng tri \u00e2n\", m\u1ed7i b\u00e0i vi\u1ebft l\u00e0 m\u1ed9t cung b\u1eadc c\u1ea3m x\u00fac ri\u00eang, d\u1ea5u \u1ea5n ri\u00eang v\u1edbi nh\u1eefng c\u00e2u chuy\u1ec7n th\u1eadt mang \u0111\u1ebfn b\u00e0i h\u1ecdc qu\u00fd gi\u00e1 \u0111\u01b0\u1ee3c ch\u1eaft l\u1ecdc t\u1eeb cu\u1ed9c s\u1ed1ng. Nh\u00e2n v\u1eadt trong m\u1ed7i c\u00e2u chuy\u1ec7n l\u00e0 nh\u1eefng con ng\u01b0\u1eddi trong \u0111\u1eddi s\u1ed1ng b\u00ecnh th\u01b0\u1eddng nh\u01b0: \u00f4ng b\u00e0, cha m\u1eb9, th\u1ea7y c\u00f4..., nh\u01b0ng t\u1ea5t c\u1ea3 h\u1ecd \u0111\u1ec1u \u0111\u01b0\u1ee3c vi\u1ebft m\u1ed9t c\u00e1ch s\u1ed1ng \u0111\u1ed9ng. M\u1eddi b\u1ea1n \u0111\u00f3n \u0111\u1ecdc.", "img": "https://www.vinabook.com/images/thumbnails/product/240x/45791_52334.jpg", "author": "Nhi\u1ec1u T\u00e1c Gi\u1ea3", "class": "vanhoc", "name": "N\u00e9t B\u00fat Tri \u00c2n - T\u1eadp 3: Th\u1eafp L\u1eeda Y\u00eau Th\u01b0\u01a1ng"}