{"publisher": "NXB Tr\u1ebb", "isbn": "8934974123057", "description": "  Chuy\u1ec7n di\u1ec5n ra \u1edf qu\u00e1n \u0110o \u0110o, qu\u00e1n \u0103n do t\u00e1c gi\u1ea3 s\u00e1ng l\u1eadp \u0111\u1ec3 nh\u1edb qu\u00ea nh\u00e0, n\u01a1i c\u00f3 ch\u1ee3 \u0110o \u0110o \u2013 ch\u1ed7 Qu\u00e1n G\u00f2 \u0111i l\u00ean \u1ea5y. B\u1edfi th\u1ebf, trong c\u00e2u truy\u1ec7n tr\u00e0n ng\u1eadp nh\u1eefng n\u1ed7i nh\u1edb, nh\u1edb m\u00f3n \u0103n, nh\u1edb gi\u1ecdng n\u00f3i, nh\u1edb th\u00f3i quen, nh\u1edb k\u1ec9 ni\u1ec7m\u2026 D\u1eabu l\u00e0 c\u00e2u chuy\u1ec7n ng\u1eadp tr\u00e0n n\u1ed7i nh\u1edb, v\u1eabn nghe trong \u0111\u00f3 nh\u1eefng ti\u1ebfng c\u01b0\u1eddi r\u1ea5t vui. \u00a0 ***\u00a0 L\u00fac th\u1eb1ng C\u1ea3i b\u1ecb th\u1eb1ng L\u00e2m \u0111\u00e1 v\u0103ng v\u00f4 l\u00f2 than, con C\u00fac \u0111i\u1ebfng ng\u01b0\u1eddi h\u00e9t gi\u1eadt v\u00e0 ch\u1ed3m t\u1edbi \u0111\u1ecbnh \u0111\u1ee1 th\u1eb1ng C\u1ea3i. Kh\u00f4ng d\u00e8 \u0111\u1ebfn ph\u00fat ch\u00f3t, c\u00e1i l\u00f2 than b\u1ecb th\u1eb1ng L\u00e2m \u0111\u00e1 bay \u0111i ch\u1ed7 kh\u00e1c, th\u00e0nh th\u1eed th\u1eb1ng C\u00e3i ng\u00e3 s\u1ea5p v\u00f4 ng\u01b0\u1eddi con C\u00fac. Hai \u0111\u1ee9a kh\u00f4ng c\u00f2n c\u00e1ch n\u00e0o kh\u00e1c l\u00e0 \u00f4m ch\u1ea7m l\u1ea5y nhau t\u00e9 l\u0103n ra \u0111\u1ea5t.\u00a0 Th\u1eb1ng L\u00e2m bi\u1ebft \u0111\u00f3 l\u00e0 chuy\u1ec7n b\u1ea5t \u0111\u1eafc d\u0129 nh\u01b0ng th\u1ea5y th\u1eb1ng C\u1ea3i \u00f4m con C\u00fac l\u00e2u qu\u00e1 kh\u00f4ng ch\u1ecbu ng\u1ed3i l\u00ean th\u00ec c\u00e1u l\u1eafm.\u00a0 M\u1eddi b\u1ea1n \u0111\u00f3n \u0111\u1ecdc.", "img": "https://www.vinabook.com/images/thumbnails/product/240x/137925_biatruocceqd-6n.jpg", "author": "Nguy\u1ec5n Nh\u1eadt \u00c1nh", "class": "vanhoc", "name": "Qu\u00e1n G\u00f2 \u0110i L\u00ean - T\u00e1i b\u1ea3n 12/2013"}