{"publisher": "NXB V\u0103n H\u00f3a V\u0103n Ngh\u1ec7", "isbn": "9786046822974", "description": "  Con ng\u01b0\u1eddi ta c\u00f3 r\u1ea5t nhi\u1ec1u ch\u1ed1n \u0111\u1ec3 \u0111i nh\u01b0ng ch\u1ec9 c\u00f3 m\u1ed9t n\u01a1i \u0111\u1ec3 tr\u1edf v\u1ec1 l\u00e0 gia \u0111\u00ecnh. Ch\u00ednh t\u1eeb cu\u1ed9c h\u00f4n nh\u00e2n c\u00f3 khi ch\u1eb3ng tr\u00f2n tr\u1ecba ta l\u1ea1i b\u1ecf t\u00fai th\u00eam cho m\u00ecnh nh\u1eefng kinh nghi\u1ec7m nho nh\u1ecf \u0111\u1ec3 gi\u1eef g\u00ecn t\u1ed5 \u1ea5m nh\u1ecf tr\u00f2n h\u01a1n. V\u00ec h\u00f4n nh\u00e2n b\u00e2y gi\u1edd kh\u00f3 l\u1eafm, n\u00ean ch\u00ednh ta ph\u1ea3i s\u1ed1ng t\u1ed1t, s\u1ed1ng c\u00f3 tr\u00e1ch nhi\u1ec7m \u0111\u1ec3 y\u00eau th\u01b0\u01a1ng cho \u0111i v\u00e0 nh\u1eadn \u0111\u1ec3 th\u1ea5y h\u00f4n nh\u00e2n lu\u00f4n l\u00e0 m\u1ed9t c\u00e1nh c\u1eeda mu\u00f4n m\u00e0u \u0111\u1ec3 m\u1ed7i ng\u01b0\u1eddi tr\u1ea3i nghi\u1ec7m v\u00e0 tr\u01b0\u1edfng th\u00e0nh. T\u00f4i th\u00edch h\u00f4n nh\u00e2n b\u00e2y gi\u1edd kh\u00f3 l\u1eafm s\u1ebd l\u00e0 m\u1ed9t c\u00e2u h\u1ecfi. \u0110\u1eebng qu\u00ean d\u1ea5u h\u1ecfi \u1ea5y s\u1ebd \u0111\u01b0\u1ee3c tr\u1ea3 l\u1eddi b\u1eb1ng ch\u00ednh th\u00e1i \u0111\u1ed9 s\u1ed1ng c\u1ee7a m\u1ed7i ng\u01b0\u1eddi v\u00e0 c\u1ea3 s\u1ef1 qu\u1ea3n l\u00fd ch\u00ednh m\u00ecnh b\u1eb1ng \u0111\u00edch \u0111\u1ebfn c\u1ee7a h\u1ea1nh ph\u00fac m\u00e0 b\u1ea1n \u0111\u00e3 ch\u1ecdn khi \u0111\u1ebfn v\u1edbi ng\u01b0\u1eddi d\u01b0ng \u0111\u1ec3 th\u00e0nh ng\u01b0\u1eddi th\u00e2n quen m\u00e3i m\u00e3i\u2026 (Ti\u1ebfn s\u0129 t\u00e2m l\u00fd Hu\u1ef3nh V\u0103n S\u01a1n) M\u1eddi b\u1ea1n \u0111\u00f3n \u0111\u1ecdc. ", "img": "https://www.vinabook.com/images/thumbnails/product/240x/197875_p66417mbt.jpg", "author": "Ho\u00e0ng My", "class": "vanhoc", "name": "\u0110\u00e0n B\u00e0 @"}