{"publisher": "NXB Kim \u0110\u1ed3ng", "isbn": "9786042091022", "description": "  \u201cD\u00f2ng m\u00e1u Trung Hoa \u0111\u1ebfn t\u00f4i kh\u00f4ng c\u00f2n nguy\u00ean v\u1eb9n n\u1eefa. Nh\u01b0ng \u0111\u00f3 l\u00e0 d\u00f2ng m\u00e1u c\u1ed9i ngu\u1ed3n, qu\u00ea cha \u0111\u00e3 h\u00f2a chung c\u00f9ng d\u00f2ng m\u00e1u Vi\u1ec7t Nam \u0111\u1ec3 l\u00e0m n\u00ean t\u00e2m t\u01b0, t\u00ecnh c\u1ea3m v\u1ea7 v\u0103n phong c\u1ee7a \u201cCh\u00e2n tr\u1eddi c\u0169\u201d. Th\u00eam v\u00e0o \u0111\u00f3 l\u00e0 cu\u1ed9c s\u1ed1ng m\u1ed9t l\u00e0ng qu\u00ea v\u1edbi nh\u1eefng s\u1ed1 ph\u1eadn c\u1ee7a con ng\u01b0\u1eddi h\u1ea9m hiu, ngh\u00e8o kh\u1ed5 m\u00e0 t\u00f4i g\u1ea7n g\u0169i, th\u00e2n y\u00eau ngay t\u1eeb khi c\u00f2n th\u01a1 \u1ea5y, \u0111\u00e3 t\u1ea1o d\u1ef1ng cho t\u00f4i \u201cc\u00e1i \u0111\u1ea5t\u201d \u0111\u1ec3 vi\u1ebft v\u0103n v\u00e0 tr\u1edf th\u00e0nh c\u1ea3m h\u1ee9ng kh\u01a1i ngu\u1ed3n cho t\u00f4i s\u00e1ng t\u00e1c\u2026\u201d Nh\u00e0 v\u0103n H\u1ed3 Dz\u1ebfnh \u201c\u2026T\u00f4i m\u1ebfn y\u00eau th\u01a1 H\u1ed3 Dz\u1ebfnh kh\u00f4ng ph\u1ea3i trong l\u00fac th\u00e1i b\u00ecnh m\u00e0 ch\u00ednh l\u00e0 \u1edf trong kh\u00f3i l\u1eeda. C\u00f3 nh\u1eefng b\u00e0i t\u00f4i y\u00eau m\u1ed9t v\u00e0i c\u00e2u nh\u01b0 b\u00e0i \u201cM\u00e0u c\u00e2y trong kh\u00f3i\u201d, c\u00f3 nh\u1eefng b\u00e0i t\u00f4i y\u00eau c\u1ea3 m\u1ed9t \u0111o\u1ea1n: \u201c\u2026 Th\u01a1 vi\u1ebft \u0111\u1eebng xong, thuy\u1ec1n tr\u00f4i ch\u1edb \u0111\u1ed7, Cho ngh\u00ecn sau l\u01a1 l\u1eedng v\u1edbi ngh\u00ecn x\u01b0a.\u201d\u201d Nh\u00e0 v\u0103n V\u0169 B\u1eb1ng", "img": "https://www.vinabook.com/images/thumbnails/product/240x/259561_p75850mimg607.jpg", "author": "H\u1ed3 Dz\u1ebfnh", "class": "vanhoc", "name": "Ch\u00e2n Tr\u1eddi C\u0169"}