{"publisher": "Th\u00e1i H\u00e0", "isbn": "8936037799407", "description": "  Nh\u01b0 ch\u00fang ta \u0111\u00e3 bi\u1ebft, m\u1ed9t ph\u1ea7n kh\u00f4ng nh\u1ecf trong kinh Ph\u1eadt \u0111\u01b0\u1ee3c vi\u1ebft theo th\u1ec3 th\u01a1 nh\u01b0: kinh Ph\u00e1p C\u00fa, Tr\u01b0\u1edfng L\u00e3o T\u0103ng K\u1ec7, Tr\u01b0\u1edfng L\u00e3o Ni K\u1ec7. T\u01b0\u01a1ng t\u1ef1, nhi\u1ec1u ph\u1ea9m trong kinh Ti\u1ec3u B\u1ed9 c\u0169ng \u0111\u01b0\u1ee3c vi\u1ebft theo th\u1ec3 th\u01a1. Ch\u00fang ta d\u1ec5 d\u00e0ng th\u1ea5y \u0111\u01b0\u1ee3c r\u1eb1ng, t\u1eeb xa x\u01b0a \u0111\u1ee9c Ph\u1eadt v\u00e0 nhi\u1ec1u v\u1ecb th\u00e1nh t\u0103ng, th\u00e1nh ni kh\u00e1c \u0111\u00e3 r\u1ea5t y\u00eau th\u00edch th\u01a1 ca c\u0169ng nh\u01b0 d\u00f9ng th\u01a1 ca \u0111\u1ec3 tr\u00ecnh b\u00e0y nh\u1eefng suy ngh\u0129 v\u00e0 gi\u00e1o l\u00fd c\u1ee7a Ph\u1eadt. Th\u01a1 thi\u1ec1n c\u1ee7a H\u00e0n Long \u1ea8n c\u0169ng v\u1eady, c\u00f4 \u0111\u1ecdng, c\u1ea3m h\u1ee9ng, gi\u00e0u nh\u1ea1c t\u00ednh, nh\u01b0ng c\u0169ng r\u1ea5t \u0111\u1ed7i d\u1ecbu d\u00e0ng. C\u00e1ch nh\u00e0 th\u01a1 mang gi\u00e1o l\u00fd Ph\u1eadt gi\u00e1o v\u00e0o th\u01a1 kh\u00f4ng h\u1ec1 khi\u00ean c\u01b0\u1ee1ng m\u00e0 t\u1ef1 nhi\u00ean qu\u00e1 \u0111\u1ed7i\u2026 D\u0129 nhi\u00ean, b\u1edfi nh\u00e0 th\u01a1 H\u00e0n Long \u1ea8n lu\u00f4n \u0111\u1ee9ng \u1edf t\u00e2m th\u01a1 m\u1ed9t nh\u00e0 s\u01b0 \u0111\u1ec3 gieo nh\u1eefng v\u1ea7n th\u01a1. Ch\u00fang ta s\u1ebd th\u1ea5y r\u1ea5t nhi\u1ec1u khi \u00f4ng m\u01b0\u1ee3n c\u00e1c h\u00ecnh \u1ea3nh c\u00f5i n\u00e0y \u0111\u1ec3 n\u00f3i v\u1ec1 v\u00f4 th\u01b0\u1eddng, v\u00f4 ng\u00e3\u2026 k\u1ec3 c\u1ea3 khi \u00f4ng khuy\u1ebfn tu m\u00e0 kh\u00f4ng h\u1ec1 n\u1eb7ng n\u1ec1 thuy\u1ebft gi\u1ea3ng, l\u1ea1i kh\u00e9o l\u00e9o mang nh\u1eefng h\u00ecnh \u1ea3nh \u0111\u1ed1i ngh\u1ecbch nhau \u0111\u1ec3 n\u00eau l\u00ean ni\u1ec1m an l\u1ea1c c\u1ee7a gi\u1ea3i tho\u00e1t. \u2026 N\u1ebfu kh\u00f4ng b\u01b0\u1edbc ch\u00e2n \u0111i Th\u00ec l\u1ea5y \u0111\u00e2u \u0111\u1ee9ng l\u1ea1i? Ki\u1ebfp ng\u01b0\u1eddi kh\u00f4ng ngang tr\u00e1i H\u1ea1nh ph\u00fac ch\u1eb3ng ai c\u1ea7n! N\u1ebfu kh\u00f4ng c\u00f3 huy\u1ec5n th\u00e2n D\u1ef1a v\u00e0o \u0111\u00e2u gi\u00e1c ng\u1ed9? N\u1ebfu tr\u1eddi kh\u00f4ng b\u00e3o t\u1ed1 Bi\u1ec3n l\u1eb7ng c\u0169ng v\u00f4 h\u1ed3n\u2026 Qua t\u1eadp th\u01a1 n\u00e0y, H\u00e0n Long \u1ea8n \u0111\u00e3 ho\u00e0n t\u1ea5t xu\u1ea5t s\u1eafc vai tr\u00f2 m\u1ed9t nh\u00e0 th\u01a1 \u2013 s\u1eed d\u1ee5ng ng\u00f4n ng\u1eef nhi\u1ec1u nh\u1ea1c t\u00ednh, d\u1ecbu d\u00e0ng, \u0111\u1ea7y c\u1ea3m h\u1ee9ng v\u00e0 chuy\u1ec3n c\u00e1c kh\u00e1i ni\u1ec7m tr\u1eebu t\u01b0\u1ee3ng sang h\u00ecnh \u1ea3nh \u0111\u1eddi th\u01b0\u1eddng. V\u00e0 c\u0169ng \u0111\u00e3 ho\u00e0n t\u1ea5t vai tr\u00f2 m\u1ed9t nh\u00e0 s\u01b0 khi gi\u1ea3i th\u00edch v\u1ec1 v\u00f4 th\u01b0\u1eddng, v\u1ec1 t\u1eeb bi, h\u1ef7 x\u1ea3\u2026 Khi ng\u00f4n ng\u1eef th\u01a1 thu\u1ea7n Vi\u1ec7t \u0111\u00e3 ng\u1ea5m v\u00e0o th\u1ecbt da x\u01b0\u01a1ng t\u1ee7y c\u1ee7a nh\u00e0 s\u01b0 H\u00e0n Long \u1ea8n, nh\u1eefng con ch\u1eef di\u1ec7u ngh\u0129a v\u00f4 th\u01b0\u1eddng c\u0169ng hi\u1ec3n l\u1ed9 th\u00e0nh hoa. Nh\u1eefng trang th\u01a1 Nh\u01b0 m\u00e2y \u0111\u1ea7u n\u00fai t\u1ef1a nh\u01b0 nh\u1eefng v\u01b0\u1eddn hoa v\u00f4 \u01b0u v\u1eady!", "img": "https://www.vinabook.com/images/thumbnails/product/240x/264262_p76234mnhumaydaunui2.jpg", "author": "H\u00e0n Long \u1ea8n", "class": "vanhoc", "name": "Nh\u01b0 M\u00e2y \u0110\u1ea7u N\u00fai"}