{"publisher": "\u0110inh T\u1ecb", "isbn": "8935212322805", "description": "  N\u1ebfu \u1edf nh\u1eefng ch\u01b0\u01a1ng \u0111\u1ea7u c\u1ee7a \u0110\u1ed3ng b\u1ea1c tr\u1eafng hoa x\u00f2e, \u00f4ng tu\u00e2n th\u1ee7 l\u1ed1i vi\u1ebft c\u1ee7a ng\u01b0\u1eddi k\u1ec3 chuy\u1ec7n bi\u1ebft h\u1ebft, t\u00e1c ph\u1ea9m b\u1ecb l\u1ea5n \u00e1t b\u1edfi m\u1ed9t gi\u1ecdng \u0111i\u1ec7u k\u1ec3 th\u00ec \u0111\u1ebfn G\u1eb7p g\u1ee1 \u1edf La Pan T\u1ea9n, ti\u1ec3u thuy\u1ebft c\u1ee7a Ma V\u0103n Kh\u00e1ng \u0111\u00e3 l\u00e0 m\u1ed9t th\u1ef1c th\u1ec3 sinh \u0111\u1ed9ng bi\u1ebft bao: t\u00e1c ph\u1ea9m c\u00f3 nhi\u1ec1u t\u1ea7ng l\u1edbp \u00fd ngh\u0129a, ch\u1ee9a nhi\u1ec1u \u1ea9n d\u1ee5 ngh\u1ec7 thu\u1eadt, h\u01b0 v\u00e0 th\u1ef1c, ti\u1ec1m th\u1ee9c, v\u00f4 th\u1ee9c \u0111an c\u00e0i v\u1edbi \u00fd th\u1ee9c s\u00e1ng r\u00f5 c\u00f3 ch\u1ee7 \u0111\u00edch; th\u1ebf gi\u1edbi hi\u1ec7n th\u1ef1c hi\u1ec7n h\u1eefu v\u00e0 th\u1ebf gi\u1edbi t\u00e2m linh, huy\u1ec1n tho\u1ea1i b\u1ed5 sung v\u00e0o nhau, nh\u00f2e m\u1edd c\u00e1c ranh gi\u1edbi, m\u00e0 t\u01b0 duy tr\u1eebu t\u01b0\u1ee3ng mu\u1ed1n ph\u00e2n \u0111\u1ecbnh r\u1ea1ch r\u00f2i. T\u00e1c ph\u1ea9m l\u00e0 s\u1ef1 t\u1ed5ng h\u1ee3p, s\u1ef1 thu h\u00fat v\u00e0o n\u00f3 nh\u1eefng th\u1ee7 ph\u00e1p c\u1ee7a ti\u1ec3u thuy\u1ebft t\u01b0 li\u1ec7u - nghi\u00ean c\u1ee9u, ti\u1ec3u thuy\u1ebft t\u1ef1 thu\u1eadt v\u00e0 k\u1ef9 thu\u1eadt d\u00f2ng \u00fd th\u1ee9c, b\u00fat ph\u00e1p t\u01b0\u1ee3ng tr\u01b0ng,v.v... - PGS. TS. Nguy\u1ec5n Ng\u1ecdc Thi\u1ec7n", "img": "https://www.vinabook.com/images/thumbnails/product/240x/265534_p76400mgapgoo.jpg", "author": "Ma V\u0103n Kh\u00e1ng", "class": "vanhoc", "name": "G\u1eb7p G\u1ee1 \u1ede La Pan T\u1ea9n"}