{"publisher": "Th\u00e1i H\u00e0", "isbn": "8936037795416", "description": " T\u00f4i kh\u00e1m ph\u00e1 r\u1eb1ng kh\u00f4ng ph\u1ea3i t\u1ea5t c\u1ea3 tri\u1ec7u ph\u00fa \u0111\u1ec1u c\u00f3 \u0111\u1ecba v\u1ecb x\u00e3 h\u1ed9i cao. Th\u1ef1c t\u1ebf, nh\u1eefng ng\u01b0\u1eddi thu\u1ed9c nh\u00f3m c\u00f3 hi\u1ec7u n\u0103ng th\u1ea5p nh\u1ea5t trong chuy\u1ec3n \u0111\u1ed5i thu nh\u1eadp th\u00e0nh t\u00e0i s\u1ea3n l\u1ea1i c\u00f3 ngh\u1ec1 nghi\u1ec7p thu\u1ed9c lo\u1ea1i \u0111\u1ecba v\u1ecb x\u00e3 h\u1ed9i cao. Trong m\u1ed9t nghi\u00ean c\u1ee9u v\u1ec1 tri\u1ec7u ph\u00fa tr\u00ean to\u00e0n qu\u1ed1c v\u00e0o n\u0103m 1980, t\u00f4i ph\u00e1t hi\u1ec7n r\u1eb1ng m\u1ed9t n\u1eeda tri\u1ec7u ph\u00fa c\u1ee7a M\u1ef9 kh\u00f4ng s\u1ed1ng trong nh\u1eefng khu th\u01b0\u1ee3ng l\u01b0u. Trong Th\u00f4i h\u00e0nh x\u1eed gi\u00e0u c\u00f3... v\u00e0 b\u1eaft \u0111\u1ea7u s\u1ed1ng nh\u01b0 tri\u1ec7u ph\u00fa th\u1eadt s\u1ef1, t\u00f4i tr\u00ecnh b\u00e0y chi ti\u1ebft t\u1ea1i sao c\u00f3 qu\u00e1 nhi\u1ec1u ng\u01b0\u1eddi kh\u00f4ng gi\u00e0u nh\u01b0ng l\u1ea1i chi ti\u00eau qu\u00e1 m\u1ee9c cho nh\u1eefng th\u1ee9 xa x\u1ec9. H\u1ecd th\u01b0\u1eddng ngh\u0129 r\u1eb1ng vi\u1ec7c thu th\u1eadp nh\u1eefng m\u00f3n \u0111\u1ed3 ch\u01a1i \u0111\u1eaft ti\u1ec1n n\u00e0y s\u1ebd gia t\u0103ng m\u1ee9c \u0111\u1ed9 th\u1ecfa m\u00e3n n\u00f3i chung c\u1ee7a m\u00ecnh v\u1edbi cu\u1ed9c s\u1ed1ng. Nh\u01b0ng nh\u01b0 b\u1ea1n s\u1ebd \u0111\u1ecdc chi ti\u1ebft, h\u1ea1nh ph\u00fac trong cu\u1ed9c s\u1ed1ng ch\u1ec9 li\u00ean quan ph\u1ea7n n\u00e0o v\u1edbi nh\u1eefng g\u00ec b\u1ea1n m\u1eb7c, l\u00e1i, \u0103n hay u\u1ed1ng. Nh\u1eefng ng\u01b0\u1eddi th\u1ecfa m\u00e3n nh\u1ea5t l\u00e0 nh\u1eefng ng\u01b0\u1eddi s\u1ed1ng th\u1ea5p h\u01a1n kh\u1ea3 n\u0103ng ti\u1ec1n b\u1ea1c c\u1ee7a h\u1ecd. Ngay trong nh\u1eefng cao \u0111i\u1ec3m g\u1ea7n \u0111\u00e2y v\u1ec1 kh\u1ea3 n\u0103ng l\u00e0m ra thu nh\u1eadp, th\u1ecb tr\u01b0\u1eddng b\u1ea5t \u0111\u1ed9ng s\u1ea3n nh\u00e0 \u1edf v\u00e0 th\u1ecb tr\u01b0\u1eddng b\u1ea5t \u0111\u1ed9ng s\u1ea3n t\u0103ng gi\u00e1, khi th\u1ef1c hi\u1ec7n cu\u1ed9c kh\u1ea3o s\u00e1t ch\u00ednh c\u1ee7a cu\u1ed1n s\u00e1ch n\u00e0y, nh\u1eefng tri\u1ec7u ph\u00fa n\u00e0y v\u1eabn duy tr\u00ec th\u00f3i quen t\u1eb1n ti\u1ec7n v\u00e0 c\u1ea7n ki\u1ec7m. (Xem chi ti\u1ebft kh\u1ea3o s\u00e1t \u1edf ph\u1ee5 l\u1ee5c A v\u00e0 ch\u00e2n dung tri\u1ec7u ph\u00fa \u1edf ph\u1ee5 l\u1ee5c B). N\u00f3i c\u00e1ch kh\u00e1c, s\u1ef1 gia t\u0103ng gi\u00e1 tr\u1ecb t\u00e0i s\u1ea3n kh\u00f4ng l\u00e0m cho \u0111a s\u1ed1 ng\u01b0\u1eddi gi\u00e0u ti\u00eau d\u00f9ng \"kh\u1ee7ng\". T\u1ea1i sao m\u1ed9t v\u00e0i ng\u01b0\u1eddi tr\u1ecb gi\u00e1 10 tri\u1ec7u, 20 tri\u1ec7u hay th\u1eadm ch\u00ed 30 tri\u1ec7u \u0111\u00f4 la ch\u1ec9 s\u1edf h\u1eefu v\u00e0i th\u1ee9 hay kh\u00f4ng c\u00f3 th\u1ee9 g\u00ec xa x\u1ec9? H\u1ecd bi\u1ebft r\u1eb1ng s\u1ef1 th\u1ecfa m\u00e3n v\u1edbi cu\u1ed9c s\u1ed1ng kh\u00f4ng ph\u1ea3i l\u00e0 m\u1ed9t \u0111\u1eb7c \u0111i\u1ec3m li\u00ean quan v\u1edbi nh\u1eefng th\u1ee9 b\u1ea1n c\u00f3 th\u1ec3 mua \u0111\u01b0\u1ee3c trong m\u1ed9t c\u1eeda h\u00e0ng. Nh\u01b0 b\u1ea1n s\u1ebd th\u1ea5y khi \u0111\u1ecdc cu\u1ed1n s\u00e1ch n\u00e0y, nh\u1eefng ng\u01b0\u1eddi n\u00e0y \u0111\u00e3 \u0111\u01b0\u1ee3c b\u1ed1 m\u1eb9 hu\u1ea5n luy\u1ec7n \u0111\u1ec3 s\u1ed1ng th\u1ea5p h\u01a1n kh\u1ea3 n\u0103ng ti\u1ec1n b\u1ea1c c\u1ee7a m\u00ecnh c\u0169ng nh\u01b0 d\u1ea1y d\u1ed7 c\u00e1ch \u0111\u1ea7u t\u01b0 v\u00e0 qu\u1ea3n l\u00fd ti\u1ec1n b\u1ea1c hi\u1ec7u qu\u1ea3. V\u00ec th\u1ebf, h\u00e0ng t\u1ec9 \u0111\u00f4 la \u0111\u1ed5 v\u00e0o nh\u1eefng chi\u1ebfn d\u1ecbch qu\u1ea3ng c\u00e1o ti\u1ebfp th\u1ecb r\u00f9m beng cho nh\u1eefng s\u1ea3n ph\u1ea9m n\u00e2ng cao \u0111\u1eb3ng c\u1ea5p ch\u1ec9 \u1ea3nh h\u01b0\u1edfng ch\u00fat \u00edt \u0111\u1ebfn phong c\u00e1ch ti\u00eau d\u00f9ng c\u1ee7a h\u1ecd. M\u1eb7c kh\u00e1c, nh\u1eefng ng\u01b0\u1eddi n\u00e0y c\u00f3 khuynh h\u01b0\u1edbng k\u1ebft giao v\u1edbi nh\u1eefng ng\u01b0\u1eddi c\u00f3 c\u00f9ng th\u00e1i \u0111\u1ed9, m\u1ed1i quan t\u00e2m, h\u00e0nh \u0111\u1ed9ng v\u00e0 ni\u1ec1m tin. M\u1eddi b\u1ea1n \u0111\u00f3n \u0111\u1ecdc.", "img": "https://www.vinabook.com/images/thumbnails/product/240x/155123_p56122mdungrave.jpg", "author": "Thomas J. Stanley, Ph.D", "class": "kinhte", "name": "\u0110\u1eebng Ra V\u1ebb Ta \u0110\u00e2y Gi\u00e0u C\u00f3"}