{"publisher": "PandaBooks", "isbn": "8935077031409", "description": "  L\u00e3nh \u0111\u1ea1o, n\u00f3i m\u1ed9t c\u00e1ch gi\u1ea3n \u0111\u01a1n l\u00e0 kh\u1ea3 n\u0103ng g\u00e2y \u1ea3nh h\u01b0\u1edfng cho ng\u01b0\u1eddi\r\nkh\u00e1c. L\u00e3nh \u0111\u1ea1o d\u1ef1a tr\u00ean gi\u00e1 tr\u1ecb \u0111\u00e3 \u0111\u01b0a kh\u00e1i ni\u1ec7m n\u00e0y l\u00ean m\u1ed9t b\u1eadc cao h\u01a1n. B\u1eb1ng\r\nl\u1eddi n\u00f3i, h\u00e0nh \u0111\u1ed9ng v\u00e0 n\u00eau g\u01b0\u01a1ng, nh\u00e0 l\u00e3nh \u0111\u1ea1o d\u1ef1a tr\u00ean gi\u00e1 tr\u1ecb t\u00ecm c\u00e1ch truy\u1ec1n\r\nc\u1ea3m h\u1ee9ng v\u00e0 \u0111\u1ed9ng vi\u00ean, s\u1eed d\u1ee5ng \u1ea3nh h\u01b0\u1edfng c\u1ee7a h\u1ecd \u0111\u1ec3 \u0111\u1ea1t \u0111\u01b0\u1ee3c \u0111i\u1ec1u quan tr\u1ecdng nh\u1ea5t. Nh\u1eb1m gi\u00fap cho nh\u1eefng ng\u01b0\u1eddi l\u00e3nh \u0111\u1ea1o hi\u1ec3u \u0111\u01b0\u1ee3c c\u00e1c gi\u00e1 tr\u1ecb \u0111\u1ec3 s\u1eb5n\r\ns\u00e0ng cam k\u1ebft v\u00e0 t\u1eadp trung \u0111\u1ec3 t\u1ea1o s\u1ef1 kh\u00e1c bi\u1ec7t c\u0169ng nh\u01b0 l\u00e0m g\u01b0\u01a1ng cho ng\u01b0\u1eddi\r\nkh\u00e1c, nh\u1eafm \u0111\u1ebfn m\u1ee5c ti\u00eau l\u00e0m cho th\u1ebf gi\u1edbi tr\u1edf n\u00ean t\u1ed1t \u0111\u1eb9p h\u01a1n b\u1eb1ng ph\u1ea1m vi \u1ea3nh\r\nh\u01b0\u1edfng c\u00e1 nh\u00e2n, kh\u00f4ng quan tr\u1ecdng ph\u1ea1m vi l\u1edbn hay nh\u1ecf,\u00a0ch\u00fang t\u00f4i xu\u1ea5t b\u1ea3n cu\u1ed1n s\u00e1ch \"4 Nguy\u00ean t\u1eafc l\u00e3nh \u0111\u1ea1o d\u1ef1a tr\u00ean gi\u00e1 tr\u1ecb\". 4\r\nNguy\u00ean T\u1eafc L\u00e3nh \u0110\u1ea1o D\u1ef1a Tr\u00ean Gi\u00e1 Tr\u1ecb quan tr\u1ecdng \u0111\u1ed1i v\u1edbi s\u1ef1 nghi\u1ec7p\r\nc\u1ee7a b\u1ea1n t\u1eeb r\u1ea5t s\u1edbm cho \u0111\u1ebfn c\u1ea3 sau n\u00e0y. B\u1ea1n c\u1ea7n thi\u1ebft ph\u1ea3i ph\u00e1t tri\u1ec3n nh\u1eefng n\u0103ng\r\nl\u1ef1c l\u00e3nh \u0111\u1ea1o n\u00e0y t\u1eeb l\u00fac b\u1eaft \u0111\u1ea7u v\u00e0 h\u1ecdc c\u00e1ch l\u00e3nh \u0111\u1ea1o c\u0169ng nh\u01b0 g\u00e2y \u1ea3nh h\u01b0\u1edfng \u0111\u1ebfn\r\nnh\u1eefng ng\u01b0\u1eddi kh\u00f4ng ph\u1ea3i d\u01b0\u1edbi quy\u1ec1n b\u1ea1n. Sau \u0111\u00f3, khi \u0111\u00e3 l\u00e0 m\u1ed9t nh\u00e0 l\u00e3nh \u0111\u1ea1o cao c\u1ea5p\r\nh\u01a1n, b\u1ea1n s\u1ebd c\u1ea3m th\u1ea5y vi\u1ec7c l\u00e3nh \u0111\u1ea1o d\u1ec5 d\u00e0ng h\u01a1n nh\u1edd qu\u00e1 tr\u00ecnh r\u00e8n luy\u1ec7n k\u0129 n\u0103ng\r\nc\u1ee7a m\u00ecnh. M\u1ecdi ng\u01b0\u1eddi s\u1ebd th\u1ef1c hi\u1ec7n theo y\u00eau c\u1ea7u c\u1ee7a b\u1ea1n kh\u00f4ng ph\u1ea3i v\u00ec b\u1ea1n l\u00e0 s\u1ebfp\r\nm\u00e0 v\u00ec b\u1ea1n bi\u1ebft c\u00e1ch g\u00e2y \u1ea3nh h\u01b0\u1edfng v\u00e0 \u0111\u1ed9ng vi\u00ean h\u1ecd. Cho d\u00f9 b\u1ea1n \u0111ang \u1edf \u0111\u00e2u tr\u00ean\r\ncon \u0111\u01b0\u1eddng s\u1ef1 nghi\u1ec7p th\u00ec k\u1ef9 n\u0103ng l\u00e3nh \u0111\u1ea1o c\u0169ng lu\u00f4n lu\u00f4n c\u1ea7n \u0111\u01b0\u1ee3c n\u00e2ng cao. Nh\u1eefng\r\nnh\u00e0 l\u00e3nh \u0111\u1ea1o gi\u1ecfi nh\u1ea5t lu\u00f4n l\u00e0m vi\u1ec7c li\u00ean t\u1ee5c \u0111\u1ec3 tr\u1edf n\u00ean t\u1ed1t h\u01a1n. ", "img": "https://www.vinabook.com/images/thumbnails/product/240x/170896_p61301m4nguyentaclanhdao.jpg", "author": "Harry M. Jeansen Kraemer", "class": "kinhte", "name": "4 Nguy\u00ean T\u1eafc L\u00e3nh \u0110\u1ea1o D\u1ef1a Tr\u00ean Gi\u00e1 Tr\u1ecb"}