{"publisher": "Th\u00e1i H\u00e0", "isbn": "8936037798561", "description": "  C\u00e1c nh\u00e0 l\u00e3nh \u0111\u1ea1o c\u1ee7a ch\u00fang ta th\u01b0\u1eddng d\u1ef1a ho\u00e0n to\u00e0n v\u00e0o ch\u1ec9 m\u1ed9t ph\u1ea9m ch\u1ea5t \u2013 tr\u00ed \u00f3c ho\u1eb7c tr\u00e1i tim ho\u1eb7c kh\u00ed ph\u00e1ch. Kh\u00f4ng may l\u00e0, khi l\u00e0m v\u1eady, b\u1ea1n ph\u1edbt l\u1edd nh\u1eefng kh\u00eda c\u1ea1nh kh\u00e1c c\u1ee7a th\u1ee9 c\u1ea7n c\u00f3 \u0111\u1ec3 th\u00e0nh c\u00f4ng. N\u1ebfu \u0111i\u1ec1u m\u00e0 t\u1ea5t c\u1ea3 c\u00e1c nh\u00e0 l\u00e3nh \u0111\u1ea1o \u0111ang c\u1ed1 g\u1eafng \u0111\u1ec3 l\u00e0m l\u00e0 th\u1ec3 hi\u1ec7n t\u00ednh ph\u00e2n t\u00edch c\u1ee9ng nh\u1eafc th\u00ec c\u00f3 th\u1ec3 h\u1ecd s\u1ebd \u0111\u1ec3 l\u1ea1i \u1ea5n t\u01b0\u1ee3ng l\u00e0 ng\u01b0\u1eddi l\u1ea1nh l\u00f9ng, v\u00f4 t\u00ecnh. Th\u1eadm ch\u00ed, nghi\u00eam tr\u1ecdng h\u01a1n, h\u1ecd s\u1ebd thi\u1ebfu \u0111i kh\u1ea3 n\u0103ng ph\u1ea3n \u1ee9ng hi\u1ec7u qu\u1ea3 v\u1edbi m\u1ed9t lo\u1ea1t nh\u1eefng t\u00ecnh hu\u1ed1ng nh\u1ea5t \u0111\u1ecbnh b\u00ean ngo\u00e0i. Trong khi \u0111\u00f3, n\u1ebfu b\u1ea1n \u0111ang mu\u1ed1n t\u1ea1o ra m\u1ed9t v\u0103n h\u00f3a y\u00eau th\u01b0\u01a1ng, b\u1ea1n l\u1ea1i c\u00f3 th\u1ec3 b\u1ecf l\u1ee1 nh\u1eefng c\u01a1 h\u1ed9i m\u00e0 m\u1ed9t nh\u00e0 l\u00e3nh \u0111\u1ea1o m\u00e1nh kh\u00f3e v\u00e0 c\u00f3 \u0111\u1ea7u \u00f3c chi\u1ebfn l\u01b0\u1ee3c h\u01a1n s\u1ebd nh\u00ecn th\u1ea5y. M\u1eb7t kh\u00e1c, n\u1ebfu d\u1ef1a h\u1eb3n v\u00e0o d\u0169ng kh\u00ed c\u00f3 \u0111\u01b0\u1ee3c nh\u1edd s\u1ef1 c\u1ee9ng r\u1eafn v\u00e0 l\u00fd l\u1ebd c\u1ee7a b\u1ea3n th\u00e2n th\u00ec c\u00f3 th\u1ec3 khi\u1ebfn b\u1ea1n \u0111\u00e1nh gi\u00e1 kh\u00f4ng \u0111\u00fang v\u1ec1 nh\u1eefng h\u1eadu qu\u1ea3 ti\u00eau c\u1ef1c c\u00f3 th\u1ec3 x\u1ea3y ra cho nh\u00e2n vi\u00ean. Ch\u00fang ta c\u1ea7n c\u00f3 m\u1ed9t quan ni\u1ec7m m\u1edbi m\u1ebb v\u1ec1 l\u00e3nh \u0111\u1ea1o v\u00e0 m\u1ed9t c\u00e1ch ti\u1ebfp c\u1eadn m\u1edbi \u0111\u1ed1i v\u1edbi vi\u1ec7c ph\u00e1t tri\u1ec3n c\u00e1c nh\u00e0 l\u00e3nh \u0111\u1ea1o. N\u1ebfu kh\u00f4ng, c\u00e1c t\u1ed5 ch\u1ee9c s\u1ebd ti\u1ebfp t\u1ee5c l\u1eb7p l\u1ea1i \u0111\u01b0\u1eddng l\u1ed1i l\u00e3nh \u0111\u1ea1o t\u1eebng t\u1ed3n t\u1ea1i, ti\u1ebfp t\u1ee5c s\u1ea3n sinh ra h\u00e0ng lo\u1ea1t nh\u1eefng nh\u00e0 l\u00e3nh \u0111\u1ea1o ch\u1ec9 c\u00f3 c\u00e1c k\u0129 n\u0103ng c\u00f3 \u0111\u01b0\u1ee3c nh\u1edd tri th\u1ee9c nh\u01b0ng \u0111\u01b0\u1ee3c trang b\u1ecb k\u00e9m c\u1ecfi \u0111\u1ec3 gi\u1ea3i quy\u1ebft nh\u1eefng v\u1ea5n \u0111\u1ec1 ng\u00e0y c\u00e0ng tr\u1edf n\u00ean ph\u1ee9c t\u1ea1p v\u00e0 r\u1ed1i b\u1eddi hi\u1ec7n nay. Cu\u1ed1n s\u00e1ch n\u00e0y n\u00eau ra ba n\u0103ng l\u1ef1c quan tr\u1ecdng nh\u1ea5t m\u00e0 c\u00e1c nh\u00e0 l\u00e3nh \u0111\u1ea1o ng\u00e0y nay ph\u1ea3i c\u00f3: l\u1eadp chi\u1ebfn l\u01b0\u1ee3c, th\u00f4ng c\u1ea3m v\u1edbi ng\u01b0\u1eddi kh\u00e1c v\u00e0 bi\u1ebft ch\u1ea5p nh\u1eadn r\u1ee7i ro \u2013 v\u00e0 c\u00f9ng l\u00fac ph\u1ea3i c\u00f3 c\u1ea3 ba n\u0103ng l\u1ef1c n\u00e0y. Trong Tr\u00ed \u00f3c, tr\u00e1i tim v\u00e0 kh\u00ed ph\u00e1ch, c\u00e1c chuy\u00ean gia v\u1ec1 k\u0129 n\u0103ng l\u00e3nh \u0111\u1ea1o David Dotlich, Peter Cairo v\u00e0 Stephen Rhinesmith l\u1eadp lu\u1eadn r\u1eb1ng \u0111\u1ec3 th\u00e0nh c\u00f4ng trong m\u1ed9t th\u1ebf gi\u1edbi ph\u1ee9c t\u1ea1p, nhi\u1ec1u \u0111an xen v\u00e0 chuy\u1ec3n \u0111\u1ed9ng nhanh ch\u00f3ng, nh\u1eefng nh\u00e0 l\u00e3nh \u0111\u1ea1o to\u00e0n di\u1ec7n ph\u1ea3i bi\u1ebft l\u1eadp chi\u1ebfn l\u01b0\u1ee3c, x\u00e2y d\u1ef1ng nh\u1eefng m\u1ed1i quan h\u1ec7 tin c\u1eady l\u1eabn nhau v\u1edbi ng\u01b0\u1eddi kh\u00e1c v\u00e0 ki\u00ean \u0111\u1ecbnh h\u00e0nh \u0111\u1ed9ng theo \u0111\u01b0\u1eddng l\u1ed1i \u0111\u00fang \u0111\u1eafn d\u1ef1a tr\u00ean c\u00e1c gi\u00e1 tr\u1ecb c\u00e1 nh\u00e2n. Nh\u1eefng nh\u00e0 l\u00e3nh \u0111\u1ea1o \u201c\u0111\u01a1n di\u1ec7n\u201d th\u01b0\u1eddng l\u00e0 s\u1ea3n ph\u1ea9m c\u1ee7a c\u00e1c ch\u01b0\u01a1ng tr\u00ecnh \u0111\u00e0o t\u1ea1o qu\u1ea3n l\u00ed truy\u1ec1n th\u1ed1ng, c\u00f3 th\u1ec3 th\u00e0nh c\u00f4ng trong ng\u1eafn h\u1ea1n, nh\u01b0ng doanh nghi\u1ec7p c\u1ee7a h\u1ecd qua th\u1eddi gian s\u1ebd th\u1ea5t b\u1ea1i.", "img": "https://www.vinabook.com/images/thumbnails/product/240x/238464_p72498mlanhdaobang.jpg", "author": "Nhi\u1ec1u t\u00e1c gi\u1ea3", "class": "kinhte", "name": "L\u00e3nh \u0110\u1ea1o B\u1eb1ng Tr\u00ed \u00d3c, Tr\u00e1i Tim V\u00e0 Kh\u00ed Ph\u00e1ch"}